<?xml version="1.0" encoding="utf-8"?>
<SoundBanksInfo Platform="Mac" BasePlatform="Mac" SchemaVersion="12" SoundbankVersion="140">
	<RootPaths>
		<ProjectRoot>/Users/etyline/Library/Application Support/Wwise2019/Bottles/Wwise2019x64/dosdevices/y:/Documents/Progetti/WwiseProjects/Blasto-X/</ProjectRoot>
		<SourceFilesRoot>/Users/etyline/Library/Application Support/Wwise2019/Bottles/Wwise2019x64/dosdevices/y:/Documents/Progetti/WwiseProjects/Blasto-X/.cache/Mac/</SourceFilesRoot>
		<SoundBanksRoot>/Users/etyline/Library/Application Support/Wwise2019/Bottles/Wwise2019x64/dosdevices/y:/Documents/Progetti/GitHub/Blasto-X/wwise/GeneratedSoundBanks/Mac/</SoundBanksRoot>
		<ExternalSourcesInputFile></ExternalSourcesInputFile>
		<ExternalSourcesOutputRoot>Y:\Documents\Progetti\WwiseProjects\Blasto-X\GeneratedSoundBanks\Mac</ExternalSourcesOutputRoot>
	</RootPaths>
	<DialogueEvents/>
	<StreamedFiles/>
	<MediaFilesNotInAnyBank/>
	<SoundBanks>
		<SoundBank Id="1355168291" Language="SFX" Hash="33147572">
			<ObjectPath>Init</ObjectPath>
			<ShortName>Init</ShortName>
			<Path>1355168291.bnk</Path>
			<IncludedAuxBusses>
				<AuxBus Id="1396213152" Name="Gameplay_Reverb" ObjectPath="\Master-Mixer Hierarchy\Default Work Unit\Master Audio Bus\SFX\Gameplay\Gameplay_Reverb"/>
				<AuxBus Id="3420137967" Name="Menu_Reverb" ObjectPath="\Master-Mixer Hierarchy\Default Work Unit\Master Audio Bus\SFX\Gameplay\Menu_Reverb"/>
			</IncludedAuxBusses>
			<GameParameters>
				<GameParameter Id="1127857866" Name="Music_Slider" ObjectPath="\Game Parameters\Default Work Unit\Music_Slider"/>
				<GameParameter Id="4140634290" Name="SFX_Slider" ObjectPath="\Game Parameters\Default Work Unit\SFX_Slider"/>
			</GameParameters>
			<StateGroups>
				<StateGroup Id="1927797142" Name="MusicTrigger" ObjectPath="\States\Default Work Unit\MusicTrigger" GUID="{96697E5E-130C-4DA5-B5E5-6EA9704D8853}">
					<States>
						<State Id="748895195" Name="None" ObjectPath="\States\Default Work Unit\MusicTrigger\None" GUID="{CC38A415-16BE-4607-839C-ADA2902C3399}"/>
						<State Id="2244230815" Name="Safe_Zone" ObjectPath="\States\Default Work Unit\MusicTrigger\Safe_Zone" GUID="{79199A5B-A4C0-4509-A52F-E03D226BA0CF}"/>
						<State Id="2764240573" Name="Combat" ObjectPath="\States\Default Work Unit\MusicTrigger\Combat" GUID="{EFE9A17D-6624-4C7D-9FE0-CCE49C1426AA}"/>
						<State Id="2716678721" Name="Victory" ObjectPath="\States\Default Work Unit\MusicTrigger\Victory" GUID="{10ED56CC-FCE7-4BBD-9760-EAE9150F8F25}"/>
						<State Id="1593864692" Name="Defeat" ObjectPath="\States\Default Work Unit\MusicTrigger\Defeat" GUID="{10F37216-78D0-418F-A547-F782AE205D2C}"/>
					</States>
				</StateGroup>
				<StateGroup Id="3502235852" Name="MusicPause" ObjectPath="\States\Default Work Unit\MusicPause" GUID="{4D9426B6-E7FB-46FC-A5C8-46FF88F401C4}">
					<States>
						<State Id="748895195" Name="None" ObjectPath="\States\Default Work Unit\MusicPause\None" GUID="{7CD4BAC8-8F6D-4AA3-B0D8-AEAFF0B6FCA1}"/>
						<State Id="3092587493" Name="Pause" ObjectPath="\States\Default Work Unit\MusicPause\Pause" GUID="{A0CE18F8-23F5-4492-9812-A996BB56F994}"/>
						<State Id="953277036" Name="Resume" ObjectPath="\States\Default Work Unit\MusicPause\Resume" GUID="{18D07B92-0EDF-4732-BECF-D59FDCCE222D}"/>
					</States>
				</StateGroup>
			</StateGroups>
		</SoundBank>
		<SoundBank Id="3161908922" Language="SFX" Hash="3340744758">
			<ObjectPath>\SoundBanks\Default Work Unit\Main</ObjectPath>
			<ShortName>Main</ShortName>
			<Path>3161908922.bnk</Path>
			<IncludedEvents>
				<Event Id="781605932" Name="asari_attack" ObjectPath="\Events\Default Work Unit\asari_attack">
					<IncludedMemoryFiles>
						<File Id="664290624" Language="SFX">
							<ShortName>Asari_Hit.wav</ShortName>
							<Path>SFX/Asari_Hit_C6B06586.wem</Path>
						</File>
						<File Id="698099617" Language="SFX">
							<ShortName>Asari_Hit_1.wav</ShortName>
							<Path>SFX/Asari_Hit_1_6FFF7F88.wem</Path>
						</File>
					</IncludedMemoryFiles>
				</Event>
				<Event Id="2365232478" Name="asari_death" ObjectPath="\Events\Default Work Unit\asari_death">
					<IncludedMemoryFiles>
						<File Id="433737940" Language="SFX">
							<ShortName>Asari_Death_1.wav</ShortName>
							<Path>SFX/Asari_Death_1_10C4C929.wem</Path>
						</File>
						<File Id="700153028" Language="SFX">
							<ShortName>Asari_Death.wav</ShortName>
							<Path>SFX/Asari_Death_10C4C929.wem</Path>
						</File>
					</IncludedMemoryFiles>
				</Event>
				<Event Id="2677732815" Name="asari_hit" ObjectPath="\Events\Default Work Unit\asari_hit">
					<IncludedMemoryFiles>
						<File Id="824239921" Language="SFX">
							<ShortName>Asari_Hurt_1.wav</ShortName>
							<Path>SFX/Asari_Hurt_1_10C4C929.wem</Path>
						</File>
						<File Id="1058901543" Language="SFX">
							<ShortName>Asari_Hurt.wav</ShortName>
							<Path>SFX/Asari_Hurt_10C4C929.wem</Path>
						</File>
					</IncludedMemoryFiles>
				</Event>
				<Event Id="2813900867" Name="blasto_attack_01" ObjectPath="\Events\Default Work Unit\blasto_attack_01">
					<IncludedMemoryFiles>
						<File Id="873558436" Language="SFX">
							<ShortName>blasto_attack.wav</ShortName>
							<Path>SFX/blasto_attack_10C4C929.wem</Path>
						</File>
					</IncludedMemoryFiles>
				</Event>
				<Event Id="2813900864" Name="blasto_attack_02" ObjectPath="\Events\Default Work Unit\blasto_attack_02">
					<IncludedMemoryFiles>
						<File Id="873558436" Language="SFX">
							<ShortName>blasto_attack.wav</ShortName>
							<Path>SFX/blasto_attack_10C4C929.wem</Path>
						</File>
					</IncludedMemoryFiles>
				</Event>
				<Event Id="2813900865" Name="blasto_attack_03" ObjectPath="\Events\Default Work Unit\blasto_attack_03">
					<IncludedMemoryFiles>
						<File Id="873558436" Language="SFX">
							<ShortName>blasto_attack.wav</ShortName>
							<Path>SFX/blasto_attack_10C4C929.wem</Path>
						</File>
					</IncludedMemoryFiles>
				</Event>
				<Event Id="108846699" Name="blasto_attack_electric" ObjectPath="\Events\Default Work Unit\blasto_attack_electric">
					<IncludedMemoryFiles>
						<File Id="70071800" Language="SFX">
							<ShortName>blasto_attack_electric.wav</ShortName>
							<Path>SFX/blasto_attack_electric_75DE97C0.wem</Path>
						</File>
					</IncludedMemoryFiles>
				</Event>
				<Event Id="3379541511" Name="blasto_attack_shoot" ObjectPath="\Events\Default Work Unit\blasto_attack_shoot">
					<IncludedMemoryFiles>
						<File Id="236823674" Language="SFX">
							<ShortName>blasto_shoot_02.wav</ShortName>
							<Path>SFX/blasto_shoot_02_10C4C929.wem</Path>
						</File>
						<File Id="1027967376" Language="SFX">
							<ShortName>blasto_shoot_01.wav</ShortName>
							<Path>SFX/blasto_shoot_01_10C4C929.wem</Path>
						</File>
					</IncludedMemoryFiles>
				</Event>
				<Event Id="2170400111" Name="blasto_death" ObjectPath="\Events\Default Work Unit\blasto_death">
					<IncludedMemoryFiles>
						<File Id="576531700" Language="SFX">
							<ShortName>Blasto_Death.wav</ShortName>
							<Path>SFX/Blasto_Death_36DF9909.wem</Path>
						</File>
						<File Id="994099388" Language="SFX">
							<ShortName>Blasto_Death_1.wav</ShortName>
							<Path>SFX/Blasto_Death_1_36DF9909.wem</Path>
						</File>
					</IncludedMemoryFiles>
				</Event>
				<Event Id="2184510782" Name="blasto_hit" ObjectPath="\Events\Default Work Unit\blasto_hit">
					<IncludedMemoryFiles>
						<File Id="651670037" Language="SFX">
							<ShortName>Blasto_Pain_1.wav</ShortName>
							<Path>SFX/Blasto_Pain_1_10C4C929.wem</Path>
						</File>
						<File Id="960000762" Language="SFX">
							<ShortName>Blasto_Pain.wav</ShortName>
							<Path>SFX/Blasto_Pain_E5ADD1ED.wem</Path>
						</File>
					</IncludedMemoryFiles>
				</Event>
				<Event Id="4121141103" Name="blasto_jump" ObjectPath="\Events\Default Work Unit\blasto_jump">
					<IncludedMemoryFiles>
						<File Id="199104505" Language="SFX">
							<ShortName>blasto_jump.wav</ShortName>
							<Path>SFX/blasto_jump_F5BFF3BE.wem</Path>
						</File>
						<File Id="906237800" Language="SFX">
							<ShortName>blasto_jump.wav</ShortName>
							<Path>SFX/blasto_jump_F5E18F5D.wem</Path>
						</File>
					</IncludedMemoryFiles>
				</Event>
				<Event Id="1932060252" Name="box_damaged" ObjectPath="\Events\Default Work Unit\box_damaged">
					<IncludedMemoryFiles>
						<File Id="576561447" Language="SFX">
							<ShortName>box_destroyed_02.wav</ShortName>
							<Path>SFX/box_destroyed_02_10C4C929.wem</Path>
						</File>
						<File Id="686514535" Language="SFX">
							<ShortName>box_damaged_01.wav</ShortName>
							<Path>SFX/box_damaged_01_10C4C929.wem</Path>
						</File>
						<File Id="963041234" Language="SFX">
							<ShortName>box_destroyed_01.wav</ShortName>
							<Path>SFX/box_destroyed_01_10C4C929.wem</Path>
						</File>
						<File Id="1060342580" Language="SFX">
							<ShortName>box_damaged_02.wav</ShortName>
							<Path>SFX/box_damaged_02_10C4C929.wem</Path>
						</File>
					</IncludedMemoryFiles>
					<AuxBusSends>
						<AuxBus Id="1396213152" Name="Gameplay_Reverb" ObjectPath="\Master-Mixer Hierarchy\Default Work Unit\Master Audio Bus\SFX\Gameplay\Gameplay_Reverb"/>
					</AuxBusSends>
				</Event>
				<Event Id="3022074870" Name="credits_play_music" ObjectPath="\Events\Default Work Unit\credits_play_music">
					<IncludedMemoryFiles>
						<File Id="655212990" Language="SFX">
							<ShortName>Crediti.wav</ShortName>
							<Path>SFX/Crediti_13448159.wem</Path>
						</File>
					</IncludedMemoryFiles>
					<AuxBusSends>
						<AuxBus Id="3420137967" Name="Menu_Reverb" ObjectPath="\Master-Mixer Hierarchy\Default Work Unit\Master Audio Bus\SFX\Gameplay\Menu_Reverb"/>
					</AuxBusSends>
				</Event>
				<Event Id="2397774794" Name="cutscene_play_music" ObjectPath="\Events\Default Work Unit\cutscene_play_music">
					<IncludedMemoryFiles>
						<File Id="74116801" Language="SFX">
							<ShortName>Cutscene.wav</ShortName>
							<Path>SFX/Cutscene_13448159.wem</Path>
						</File>
					</IncludedMemoryFiles>
					<AuxBusSends>
						<AuxBus Id="1396213152" Name="Gameplay_Reverb" ObjectPath="\Master-Mixer Hierarchy\Default Work Unit\Master Audio Bus\SFX\Gameplay\Gameplay_Reverb"/>
					</AuxBusSends>
				</Event>
				<Event Id="2369939213" Name="desert_play_boss_music" ObjectPath="\Events\Default Work Unit\desert_play_boss_music">
					<IncludedMemoryFiles>
						<File Id="54396663" Language="SFX">
							<ShortName>Mainsection\Drums_159bpm_34beats_Var1.wav</ShortName>
							<Path>SFX/Mainsection/Drums_159bpm_34beats_Var1_E0B2C827.wem</Path>
						</File>
						<File Id="101960814" Language="SFX">
							<ShortName>Mainsection\PCM_159bpm_34beats_Var1.wav</ShortName>
							<Path>SFX/Mainsection/PCM_159bpm_34beats_Var1_E0B2C827.wem</Path>
						</File>
						<File Id="120784556" Language="SFX">
							<ShortName>Intro\PCM_159bpm_24beats_Intro.wav</ShortName>
							<Path>SFX/Intro/PCM_159bpm_24beats_Intro_E0B2C827.wem</Path>
						</File>
						<File Id="246289132" Language="SFX">
							<ShortName>Mainsection\SquareArp_159bpm_34beats_Var1.wav</ShortName>
							<Path>SFX/Mainsection/SquareArp_159bpm_34beats_Var1_E0B2C827.wem</Path>
						</File>
						<File Id="268480373" Language="SFX">
							<ShortName>Intro\Bass_159bpm_24beats_Intro.wav</ShortName>
							<Path>SFX/Intro/Bass_159bpm_24beats_Intro_E0B2C827.wem</Path>
						</File>
						<File Id="297666351" Language="SFX">
							<ShortName>Intro\Drums_159bpm_24beats_Intro.wav</ShortName>
							<Path>SFX/Intro/Drums_159bpm_24beats_Intro_E0B2C827.wem</Path>
						</File>
						<File Id="375374430" Language="SFX">
							<ShortName>Mainsection\SquareHold_159bpm_34beats_Var1.wav</ShortName>
							<Path>SFX/Mainsection/SquareHold_159bpm_34beats_Var1_E0B2C827.wem</Path>
						</File>
						<File Id="842083637" Language="SFX">
							<ShortName>Intro\Square_159bpm_24beats_Intro.wav</ShortName>
							<Path>SFX/Intro/Square_159bpm_24beats_Intro_E0B2C827.wem</Path>
						</File>
						<File Id="1043363006" Language="SFX">
							<ShortName>Mainsection\Bass_159bpm_34beats_Var1.wav</ShortName>
							<Path>SFX/Mainsection/Bass_159bpm_34beats_Var1_E0B2C827.wem</Path>
						</File>
					</IncludedMemoryFiles>
				</Event>
				<Event Id="1387614411" Name="desert_play_music" ObjectPath="\Events\Default Work Unit\desert_play_music">
					<IncludedMemoryFiles>
						<File Id="529910" Language="SFX">
							<ShortName>Drums_146bpm_2beats_Trans.wav</ShortName>
							<Path>SFX/Drums_146bpm_2beats_Trans_E0B2C827.wem</Path>
						</File>
						<File Id="78367596" Language="SFX">
							<ShortName>Bass_146bpm_8beats_Var3_Intro.wav</ShortName>
							<Path>SFX/Bass_146bpm_8beats_Var3_Intro_E0B2C827.wem</Path>
						</File>
						<File Id="80720681" Language="SFX">
							<ShortName>Sine_146bpm_8beats_Var1_Intro.wav</ShortName>
							<Path>SFX/Sine_146bpm_8beats_Var1_Intro_E0B2C827.wem</Path>
						</File>
						<File Id="84753949" Language="SFX">
							<ShortName>Bass_146bpm_8beats_Var1_Intro.wav</ShortName>
							<Path>SFX/Bass_146bpm_8beats_Var1_Intro_E0B2C827.wem</Path>
						</File>
						<File Id="125472727" Language="SFX">
							<ShortName>Bass_160bpm_16beats_SEC1_Var4.wav</ShortName>
							<Path>SFX/Bass_160bpm_16beats_SEC1_Var4_E0B2C827.wem</Path>
						</File>
						<File Id="130382283" Language="SFX">
							<ShortName>Square2_160bpm_16beats_SEC1_Var2.wav</ShortName>
							<Path>SFX/Square2_160bpm_16beats_SEC1_Var2_E0B2C827.wem</Path>
						</File>
						<File Id="147685657" Language="SFX">
							<ShortName>Sine_146bpm_8beats_Var2_Intro.wav</ShortName>
							<Path>SFX/Sine_146bpm_8beats_Var2_Intro_E0B2C827.wem</Path>
						</File>
						<File Id="190285408" Language="SFX">
							<ShortName>Saw_146bpm_8beats_Var1_Intro.wav</ShortName>
							<Path>SFX/Saw_146bpm_8beats_Var1_Intro_E0B2C827.wem</Path>
						</File>
						<File Id="284642979" Language="SFX">
							<ShortName>Bass_160bpm_16beats_SEC1_Var3.wav</ShortName>
							<Path>SFX/Bass_160bpm_16beats_SEC1_Var3_E0B2C827.wem</Path>
						</File>
						<File Id="291818240" Language="SFX">
							<ShortName>Sine_146bpm_8beats_Var3_Intro.wav</ShortName>
							<Path>SFX/Sine_146bpm_8beats_Var3_Intro_E0B2C827.wem</Path>
						</File>
						<File Id="359953739" Language="SFX">
							<ShortName>Drums_160bpm_8beats_SEC1_Var1.wav</ShortName>
							<Path>SFX/Drums_160bpm_8beats_SEC1_Var1_E0B2C827.wem</Path>
						</File>
						<File Id="411829240" Language="SFX">
							<ShortName>Square1_160bpm_16beats_SEC1_Var2.wav</ShortName>
							<Path>SFX/Square1_160bpm_16beats_SEC1_Var2_E0B2C827.wem</Path>
						</File>
						<File Id="479695179" Language="SFX">
							<ShortName>Saw_146bpm_8beats_Var2_Intro.wav</ShortName>
							<Path>SFX/Saw_146bpm_8beats_Var2_Intro_E0B2C827.wem</Path>
						</File>
						<File Id="497294975" Language="SFX">
							<ShortName>Square1_160bpm_16beats_SEC1_Var3.wav</ShortName>
							<Path>SFX/Square1_160bpm_16beats_SEC1_Var3_E0B2C827.wem</Path>
						</File>
						<File Id="513034443" Language="SFX">
							<ShortName>Drums_146bpm_8beats_Var3_Intro.wav</ShortName>
							<Path>SFX/Drums_146bpm_8beats_Var3_Intro_E0B2C827.wem</Path>
						</File>
						<File Id="530189470" Language="SFX">
							<ShortName>Drums_160bpm_16beats_SEC1_Var2.wav</ShortName>
							<Path>SFX/Drums_160bpm_16beats_SEC1_Var2_E0B2C827.wem</Path>
						</File>
						<File Id="532635487" Language="SFX">
							<ShortName>Bass_160bpm_16beats_SEC1_Var2.wav</ShortName>
							<Path>SFX/Bass_160bpm_16beats_SEC1_Var2_E0B2C827.wem</Path>
						</File>
						<File Id="571519495" Language="SFX">
							<ShortName>Square2_160bpm_16beats_SEC1_Var4.wav</ShortName>
							<Path>SFX/Square2_160bpm_16beats_SEC1_Var4_E0B2C827.wem</Path>
						</File>
						<File Id="662951955" Language="SFX">
							<ShortName>Drums_146bpm_8beats_Var2_Intro.wav</ShortName>
							<Path>SFX/Drums_146bpm_8beats_Var2_Intro_E0B2C827.wem</Path>
						</File>
						<File Id="773557607" Language="SFX">
							<ShortName>Bass_160bpm_8beats_SEC1_Var1.wav</ShortName>
							<Path>SFX/Bass_160bpm_8beats_SEC1_Var1_E0B2C827.wem</Path>
						</File>
						<File Id="881476376" Language="SFX">
							<ShortName>Square1_160bpm_8beats_SEC1_Var1.wav</ShortName>
							<Path>SFX/Square1_160bpm_8beats_SEC1_Var1_E0B2C827.wem</Path>
						</File>
						<File Id="918092539" Language="SFX">
							<ShortName>Square2_160bpm_8beats_SEC1_Var1.wav</ShortName>
							<Path>SFX/Square2_160bpm_8beats_SEC1_Var1_E0B2C827.wem</Path>
						</File>
						<File Id="920312746" Language="SFX">
							<ShortName>Drums_146bpm_8beats_Var1_Intro.wav</ShortName>
							<Path>SFX/Drums_146bpm_8beats_Var1_Intro_E0B2C827.wem</Path>
						</File>
						<File Id="950261896" Language="SFX">
							<ShortName>Bass_146bpm_2beats_Trans.wav</ShortName>
							<Path>SFX/Bass_146bpm_2beats_Trans_E0B2C827.wem</Path>
						</File>
						<File Id="966018975" Language="SFX">
							<ShortName>Bass_146bpm_8beats_Var2_Intro.wav</ShortName>
							<Path>SFX/Bass_146bpm_8beats_Var2_Intro_E0B2C827.wem</Path>
						</File>
						<File Id="986107003" Language="SFX">
							<ShortName>Saw_146bpm_8beats_Var3_Intro.wav</ShortName>
							<Path>SFX/Saw_146bpm_8beats_Var3_Intro_E0B2C827.wem</Path>
						</File>
						<File Id="1040950207" Language="SFX">
							<ShortName>Drums_160bpm_16beats_SEC1_Var3.wav</ShortName>
							<Path>SFX/Drums_160bpm_16beats_SEC1_Var3_E0B2C827.wem</Path>
						</File>
						<File Id="1060274405" Language="SFX">
							<ShortName>Drums_160bpm_16beats_SEC1_Var4.wav</ShortName>
							<Path>SFX/Drums_160bpm_16beats_SEC1_Var4_E0B2C827.wem</Path>
						</File>
					</IncludedMemoryFiles>
					<SwitchContainers>
						<SwitchContainer SwitchValue="{79199A5B-A4C0-4509-A52F-E03D226BA0CF}">
							<Media>
								<File Id="78367596"/>
								<File Id="80720681"/>
								<File Id="84753949"/>
								<File Id="147685657"/>
								<File Id="190285408"/>
								<File Id="291818240"/>
								<File Id="479695179"/>
								<File Id="513034443"/>
								<File Id="662951955"/>
								<File Id="920312746"/>
								<File Id="966018975"/>
								<File Id="986107003"/>
							</Media>
						</SwitchContainer>
						<SwitchContainer SwitchValue="{EFE9A17D-6624-4C7D-9FE0-CCE49C1426AA}">
							<Media>
								<File Id="125472727"/>
								<File Id="130382283"/>
								<File Id="284642979"/>
								<File Id="359953739"/>
								<File Id="411829240"/>
								<File Id="497294975"/>
								<File Id="530189470"/>
								<File Id="532635487"/>
								<File Id="571519495"/>
								<File Id="773557607"/>
								<File Id="881476376"/>
								<File Id="918092539"/>
								<File Id="1040950207"/>
								<File Id="1060274405"/>
							</Media>
						</SwitchContainer>
					</SwitchContainers>
				</Event>
				<Event Id="362522750" Name="gameover_play_music" ObjectPath="\Events\Default Work Unit\gameover_play_music">
					<IncludedMemoryFiles>
						<File Id="479506601" Language="SFX">
							<ShortName>Lose_112bpm_8beats.wav</ShortName>
							<Path>SFX/Lose_112bpm_8beats_E0B2C827.wem</Path>
						</File>
						<File Id="664654215" Language="SFX">
							<ShortName>Win_112bpm_8beats.wav</ShortName>
							<Path>SFX/Win_112bpm_8beats_E0B2C827.wem</Path>
						</File>
					</IncludedMemoryFiles>
					<SwitchContainers>
						<SwitchContainer SwitchValue="{10F37216-78D0-418F-A547-F782AE205D2C}">
							<Media>
								<File Id="479506601"/>
							</Media>
						</SwitchContainer>
						<SwitchContainer SwitchValue="{10ED56CC-FCE7-4BBD-9760-EAE9150F8F25}">
							<Media>
								<File Id="664654215"/>
							</Media>
						</SwitchContainer>
					</SwitchContainers>
				</Event>
				<Event Id="1604534730" Name="gun_death" ObjectPath="\Events\Default Work Unit\gun_death">
					<IncludedMemoryFiles>
						<File Id="36167455" Language="SFX">
							<ShortName>gun_death.wav</ShortName>
							<Path>SFX/gun_death_36DF9909.wem</Path>
						</File>
					</IncludedMemoryFiles>
				</Event>
				<Event Id="3103876737" Name="gun_explosion" ObjectPath="\Events\Default Work Unit\gun_explosion">
					<IncludedMemoryFiles>
						<File Id="610667664" Language="SFX">
							<ShortName>gun_explosion.wav</ShortName>
							<Path>SFX/gun_explosion_36DF9909.wem</Path>
						</File>
					</IncludedMemoryFiles>
				</Event>
				<Event Id="1193614498" Name="gun_granade" ObjectPath="\Events\Default Work Unit\gun_granade">
					<IncludedMemoryFiles>
						<File Id="197144331" Language="SFX">
							<ShortName>gun_granade.wav</ShortName>
							<Path>SFX/gun_granade_36DF9909.wem</Path>
						</File>
					</IncludedMemoryFiles>
				</Event>
				<Event Id="1475881115" Name="gun_hit" ObjectPath="\Events\Default Work Unit\gun_hit">
					<IncludedMemoryFiles>
						<File Id="931164490" Language="SFX">
							<ShortName>gun_pain.wav</ShortName>
							<Path>SFX/gun_pain_36DF9909.wem</Path>
						</File>
					</IncludedMemoryFiles>
				</Event>
				<Event Id="2177962710" Name="gun_rifle" ObjectPath="\Events\Default Work Unit\gun_rifle">
					<IncludedMemoryFiles>
						<File Id="463013555" Language="SFX">
							<ShortName>gun_rifle_02.wav</ShortName>
							<Path>SFX/gun_rifle_02_36DF9909.wem</Path>
						</File>
						<File Id="776870156" Language="SFX">
							<ShortName>gun_rifle_01.wav</ShortName>
							<Path>SFX/gun_rifle_01_36DF9909.wem</Path>
						</File>
					</IncludedMemoryFiles>
				</Event>
				<Event Id="2198651788" Name="gun_rocket" ObjectPath="\Events\Default Work Unit\gun_rocket">
					<IncludedMemoryFiles>
						<File Id="877342220" Language="SFX">
							<ShortName>gun_rocket.wav</ShortName>
							<Path>SFX/gun_rocket_36DF9909.wem</Path>
						</File>
					</IncludedMemoryFiles>
				</Event>
				<Event Id="960940028" Name="jaw_attack" ObjectPath="\Events\Default Work Unit\jaw_attack">
					<IncludedMemoryFiles>
						<File Id="270783161" Language="SFX">
							<ShortName>TheJaw_Melee.wav</ShortName>
							<Path>SFX/TheJaw_Melee_36DF9909.wem</Path>
						</File>
						<File Id="738058413" Language="SFX">
							<ShortName>TheJaw_Melee_1.wav</ShortName>
							<Path>SFX/TheJaw_Melee_1_B5C3F710.wem</Path>
						</File>
					</IncludedMemoryFiles>
				</Event>
				<Event Id="4202733843" Name="jaw_charge_mid" ObjectPath="\Events\Default Work Unit\jaw_charge_mid">
					<IncludedMemoryFiles>
						<File Id="468362828" Language="SFX">
							<ShortName>TheJaw_ChargeSteps.wav</ShortName>
							<Path>SFX/TheJaw_ChargeSteps_D79FB2B7.wem</Path>
						</File>
					</IncludedMemoryFiles>
				</Event>
				<Event Id="203922817" Name="jaw_charge_start" ObjectPath="\Events\Default Work Unit\jaw_charge_start">
					<IncludedMemoryFiles>
						<File Id="540479182" Language="SFX">
							<ShortName>charge_start.wav</ShortName>
							<Path>SFX/charge_start_C7A42C13.wem</Path>
						</File>
					</IncludedMemoryFiles>
				</Event>
				<Event Id="4175176572" Name="jaw_charghe_end" ObjectPath="\Events\Default Work Unit\jaw_charghe_end">
					<IncludedMemoryFiles>
						<File Id="994098824" Language="SFX">
							<ShortName>charge_end.wav</ShortName>
							<Path>SFX/charge_end_10C4C929.wem</Path>
						</File>
					</IncludedMemoryFiles>
				</Event>
				<Event Id="434562478" Name="jaw_death" ObjectPath="\Events\Default Work Unit\jaw_death">
					<IncludedMemoryFiles>
						<File Id="699931811" Language="SFX">
							<ShortName>TheJaw_Death.wav</ShortName>
							<Path>SFX/TheJaw_Death_36DF9909.wem</Path>
						</File>
					</IncludedMemoryFiles>
				</Event>
				<Event Id="2032028959" Name="jaw_earthquake" ObjectPath="\Events\Default Work Unit\jaw_earthquake">
					<IncludedMemoryFiles>
						<File Id="506815580" Language="SFX">
							<ShortName>TheJaw_Earthquake1.wav</ShortName>
							<Path>SFX/TheJaw_Earthquake1_B488CD10.wem</Path>
						</File>
						<File Id="644490089" Language="SFX">
							<ShortName>TheJaw_Earthquake.wav</ShortName>
							<Path>SFX/TheJaw_Earthquake_10C4C929.wem</Path>
						</File>
					</IncludedMemoryFiles>
				</Event>
				<Event Id="2816955807" Name="jaw_hit" ObjectPath="\Events\Default Work Unit\jaw_hit">
					<IncludedMemoryFiles>
						<File Id="141037040" Language="SFX">
							<ShortName>TheJaw_Pain.wav</ShortName>
							<Path>SFX/TheJaw_Pain_688F0AC4.wem</Path>
						</File>
						<File Id="862998868" Language="SFX">
							<ShortName>TheJaw_Pain_1.wav</ShortName>
							<Path>SFX/TheJaw_Pain_1_597D9EC9.wem</Path>
						</File>
					</IncludedMemoryFiles>
				</Event>
				<Event Id="4128209780" Name="krogan_attack" ObjectPath="\Events\Default Work Unit\krogan_attack">
					<IncludedMemoryFiles>
						<File Id="724930924" Language="SFX">
							<ShortName>Krogan_Hit.wav</ShortName>
							<Path>SFX/Krogan_Hit_A918E6C2.wem</Path>
						</File>
						<File Id="974791290" Language="SFX">
							<ShortName>Krogan_Hit_1.wav</ShortName>
							<Path>SFX/Krogan_Hit_1_10C4C929.wem</Path>
						</File>
					</IncludedMemoryFiles>
				</Event>
				<Event Id="553065750" Name="krogan_death" ObjectPath="\Events\Default Work Unit\krogan_death">
					<IncludedMemoryFiles>
						<File Id="434899562" Language="SFX">
							<ShortName>Krogan_Death.wav</ShortName>
							<Path>SFX/Krogan_Death_B20D504A.wem</Path>
						</File>
						<File Id="759876276" Language="SFX">
							<ShortName>Krogan_Death_1.wav</ShortName>
							<Path>SFX/Krogan_Death_1_2A584E11.wem</Path>
						</File>
					</IncludedMemoryFiles>
				</Event>
				<Event Id="2255747255" Name="krogan_hit" ObjectPath="\Events\Default Work Unit\krogan_hit">
					<IncludedMemoryFiles>
						<File Id="291266225" Language="SFX">
							<ShortName>Krogan_Pain_1.wav</ShortName>
							<Path>SFX/Krogan_Pain_1_76ACA45F.wem</Path>
						</File>
						<File Id="748558749" Language="SFX">
							<ShortName>Krogan_Pain.wav</ShortName>
							<Path>SFX/Krogan_Pain_04A54A20.wem</Path>
						</File>
					</IncludedMemoryFiles>
				</Event>
				<Event Id="1481775072" Name="kronus_attack" ObjectPath="\Events\Default Work Unit\kronus_attack">
					<IncludedMemoryFiles>
						<File Id="593831453" Language="SFX">
							<ShortName>punch.wav</ShortName>
							<Path>SFX/punch_10C4C929.wem</Path>
						</File>
					</IncludedMemoryFiles>
				</Event>
				<Event Id="808085602" Name="kronus_death_I" ObjectPath="\Events\Default Work Unit\kronus_death_I">
					<IncludedMemoryFiles>
						<File Id="144837207" Language="SFX">
							<ShortName>death_01.wav</ShortName>
							<Path>SFX/death_01_10C4C929.wem</Path>
						</File>
					</IncludedMemoryFiles>
					<ActionSetState>
						<ActionSetStateEntry Id="4059809460" Name="Act_II" ObjectPath="\States\Default Work Unit\BossFase\Act_II"/>
					</ActionSetState>
				</Event>
				<Event Id="885150255" Name="kronus_death_II" ObjectPath="\Events\Default Work Unit\kronus_death_II">
					<IncludedMemoryFiles>
						<File Id="232379220" Language="SFX">
							<ShortName>death_02.wav</ShortName>
							<Path>SFX/death_02_10C4C929.wem</Path>
						</File>
					</IncludedMemoryFiles>
					<ActionSetState>
						<ActionSetStateEntry Id="2740571445" Name="Act_III" ObjectPath="\States\Default Work Unit\BossFase\Act_III"/>
					</ActionSetState>
				</Event>
				<Event Id="1021796244" Name="kronus_death_III" ObjectPath="\Events\Default Work Unit\kronus_death_III">
					<IncludedMemoryFiles>
						<File Id="240090266" Language="SFX">
							<ShortName>death_03.wav</ShortName>
							<Path>SFX/death_03_10C4C929.wem</Path>
						</File>
					</IncludedMemoryFiles>
				</Event>
				<Event Id="4167233094" Name="kronus_lava" ObjectPath="\Events\Default Work Unit\kronus_lava">
					<IncludedMemoryFiles>
						<File Id="253122742" Language="SFX">
							<ShortName>lava.wav</ShortName>
							<Path>SFX/lava_10C4C929.wem</Path>
						</File>
					</IncludedMemoryFiles>
				</Event>
				<Event Id="1664507547" Name="kronus_move" ObjectPath="\Events\Default Work Unit\kronus_move">
					<IncludedMemoryFiles>
						<File Id="684205669" Language="SFX">
							<ShortName>move.wav</ShortName>
							<Path>SFX/move_10C4C929.wem</Path>
						</File>
					</IncludedMemoryFiles>
				</Event>
				<Event Id="2203952148" Name="kronus_pain" ObjectPath="\Events\Default Work Unit\kronus_pain">
					<IncludedMemoryFiles>
						<File Id="168543833" Language="SFX">
							<ShortName>hit_01_shout.wav</ShortName>
							<Path>SFX/hit_01_shout_10C4C929.wem</Path>
						</File>
						<File Id="323645882" Language="SFX">
							<ShortName>hit_02_shout.wav</ShortName>
							<Path>SFX/hit_02_shout_10C4C929.wem</Path>
						</File>
						<File Id="597767144" Language="SFX">
							<ShortName>hit_03.wav</ShortName>
							<Path>SFX/hit_03_10C4C929.wem</Path>
						</File>
						<File Id="682298513" Language="SFX">
							<ShortName>hit_01_spark.wav</ShortName>
							<Path>SFX/hit_01_spark_10C4C929.wem</Path>
						</File>
						<File Id="808003633" Language="SFX">
							<ShortName>hit_02_spark.wav</ShortName>
							<Path>SFX/hit_02_spark_10C4C929.wem</Path>
						</File>
					</IncludedMemoryFiles>
					<DefaultSwitchValue>{84B70B2B-F10C-497B-8ECA-D9461A3C8CB2}</DefaultSwitchValue>
					<SwitchContainers>
						<SwitchContainer SwitchValue="{84B70B2B-F10C-497B-8ECA-D9461A3C8CB2}">
							<Media>
								<File Id="168543833"/>
								<File Id="682298513"/>
							</Media>
						</SwitchContainer>
						<SwitchContainer SwitchValue="{C61D768C-7BB7-4F28-A38C-243303C01010}">
							<Media>
								<File Id="323645882"/>
								<File Id="808003633"/>
							</Media>
						</SwitchContainer>
						<SwitchContainer SwitchValue="{A97014C2-3DDD-4A7F-8122-ADEA83AD1341}">
							<Media>
								<File Id="597767144"/>
							</Media>
						</SwitchContainer>
					</SwitchContainers>
				</Event>
				<Event Id="578187831" Name="kronus_quake" ObjectPath="\Events\Default Work Unit\kronus_quake">
					<IncludedMemoryFiles>
						<File Id="80674624" Language="SFX">
							<ShortName>stomp_quake.wav</ShortName>
							<Path>SFX/stomp_quake_10C4C929.wem</Path>
						</File>
						<File Id="865811504" Language="SFX">
							<ShortName>stomp.wav</ShortName>
							<Path>SFX/stomp_10C4C929.wem</Path>
						</File>
					</IncludedMemoryFiles>
					<DefaultSwitchValue>{84B70B2B-F10C-497B-8ECA-D9461A3C8CB2}</DefaultSwitchValue>
					<SwitchContainers>
						<SwitchContainer SwitchValue="{84B70B2B-F10C-497B-8ECA-D9461A3C8CB2}">
							<Media>
								<File Id="80674624"/>
							</Media>
						</SwitchContainer>
						<SwitchContainer SwitchValue="{C61D768C-7BB7-4F28-A38C-243303C01010}">
							<Media>
								<File Id="865811504"/>
							</Media>
						</SwitchContainer>
						<SwitchContainer SwitchValue="{A97014C2-3DDD-4A7F-8122-ADEA83AD1341}">
							<Media>
								<File Id="865811504"/>
							</Media>
						</SwitchContainer>
					</SwitchContainers>
				</Event>
				<Event Id="728232404" Name="kronus_rocket" ObjectPath="\Events\Default Work Unit\kronus_rocket">
					<IncludedMemoryFiles>
						<File Id="252859808" Language="SFX">
							<ShortName>rocket_01.wav</ShortName>
							<Path>SFX/rocket_01_10C4C929.wem</Path>
						</File>
						<File Id="1010106924" Language="SFX">
							<ShortName>rocket_02.wav</ShortName>
							<Path>SFX/rocket_02_10C4C929.wem</Path>
						</File>
					</IncludedMemoryFiles>
					<DefaultSwitchValue>{84B70B2B-F10C-497B-8ECA-D9461A3C8CB2}</DefaultSwitchValue>
					<SwitchContainers>
						<SwitchContainer SwitchValue="{84B70B2B-F10C-497B-8ECA-D9461A3C8CB2}">
							<Media>
								<File Id="252859808"/>
							</Media>
						</SwitchContainer>
						<SwitchContainer SwitchValue="{C61D768C-7BB7-4F28-A38C-243303C01010}">
							<Media>
								<File Id="1010106924"/>
							</Media>
						</SwitchContainer>
					</SwitchContainers>
				</Event>
				<Event Id="974337402" Name="kronus_shotgun" ObjectPath="\Events\Default Work Unit\kronus_shotgun">
					<IncludedMemoryFiles>
						<File Id="257022896" Language="SFX">
							<ShortName>shotgun_01.wav</ShortName>
							<Path>SFX/shotgun_01_10C4C929.wem</Path>
						</File>
						<File Id="446968649" Language="SFX">
							<ShortName>shotgun_02.wav</ShortName>
							<Path>SFX/shotgun_02_10C4C929.wem</Path>
						</File>
						<File Id="737917791" Language="SFX">
							<ShortName>shotgun_03.wav</ShortName>
							<Path>SFX/shotgun_03_10C4C929.wem</Path>
						</File>
					</IncludedMemoryFiles>
					<DefaultSwitchValue>{84B70B2B-F10C-497B-8ECA-D9461A3C8CB2}</DefaultSwitchValue>
					<SwitchContainers>
						<SwitchContainer SwitchValue="{84B70B2B-F10C-497B-8ECA-D9461A3C8CB2}">
							<Media>
								<File Id="257022896"/>
							</Media>
						</SwitchContainer>
						<SwitchContainer SwitchValue="{C61D768C-7BB7-4F28-A38C-243303C01010}">
							<Media>
								<File Id="446968649"/>
							</Media>
						</SwitchContainer>
						<SwitchContainer SwitchValue="{A97014C2-3DDD-4A7F-8122-ADEA83AD1341}">
							<Media>
								<File Id="737917791"/>
							</Media>
						</SwitchContainer>
					</SwitchContainers>
				</Event>
				<Event Id="4008750564" Name="leg_01_death" ObjectPath="\Events\Default Work Unit\leg_01_death">
					<IncludedMemoryFiles>
						<File Id="623310563" Language="SFX">
							<ShortName>leg01_death_01.wav</ShortName>
							<Path>SFX/leg01_death_01_10C4C929.wem</Path>
						</File>
						<File Id="1010954485" Language="SFX">
							<ShortName>leg01_death_02.wav</ShortName>
							<Path>SFX/leg01_death_02_10C4C929.wem</Path>
						</File>
					</IncludedMemoryFiles>
					<DefaultSwitchValue>{84B70B2B-F10C-497B-8ECA-D9461A3C8CB2}</DefaultSwitchValue>
					<SwitchContainers>
						<SwitchContainer SwitchValue="{84B70B2B-F10C-497B-8ECA-D9461A3C8CB2}">
							<Media>
								<File Id="623310563"/>
							</Media>
						</SwitchContainer>
						<SwitchContainer SwitchValue="{C61D768C-7BB7-4F28-A38C-243303C01010}">
							<Media>
								<File Id="1010954485"/>
							</Media>
						</SwitchContainer>
					</SwitchContainers>
					<ActionSetState>
						<ActionSetStateEntry Id="4059809460" Name="Act_II" ObjectPath="\States\Default Work Unit\BossFase\Act_II"/>
					</ActionSetState>
				</Event>
				<Event Id="1136551430" Name="leg_01_pain" ObjectPath="\Events\Default Work Unit\leg_01_pain">
					<IncludedMemoryFiles>
						<File Id="69377252" Language="SFX">
							<ShortName>leg01_pain_02.wav</ShortName>
							<Path>SFX/leg01_pain_02_10C4C929.wem</Path>
						</File>
						<File Id="1064074779" Language="SFX">
							<ShortName>leg01_pain_01.wav</ShortName>
							<Path>SFX/leg01_pain_01_10C4C929.wem</Path>
						</File>
					</IncludedMemoryFiles>
					<DefaultSwitchValue>{84B70B2B-F10C-497B-8ECA-D9461A3C8CB2}</DefaultSwitchValue>
					<SwitchContainers>
						<SwitchContainer SwitchValue="{84B70B2B-F10C-497B-8ECA-D9461A3C8CB2}">
							<Media>
								<File Id="1064074779"/>
							</Media>
						</SwitchContainer>
						<SwitchContainer SwitchValue="{C61D768C-7BB7-4F28-A38C-243303C01010}">
							<Media>
								<File Id="69377252"/>
							</Media>
						</SwitchContainer>
					</SwitchContainers>
				</Event>
				<Event Id="3263475499" Name="leg_02_death" ObjectPath="\Events\Default Work Unit\leg_02_death">
					<IncludedMemoryFiles>
						<File Id="554847374" Language="SFX">
							<ShortName>leg02_death_02.wav</ShortName>
							<Path>SFX/leg02_death_02_10C4C929.wem</Path>
						</File>
						<File Id="1059935185" Language="SFX">
							<ShortName>leg02_death_01.wav</ShortName>
							<Path>SFX/leg02_death_01_10C4C929.wem</Path>
						</File>
					</IncludedMemoryFiles>
					<DefaultSwitchValue>{84B70B2B-F10C-497B-8ECA-D9461A3C8CB2}</DefaultSwitchValue>
					<SwitchContainers>
						<SwitchContainer SwitchValue="{84B70B2B-F10C-497B-8ECA-D9461A3C8CB2}">
							<Media>
								<File Id="1059935185"/>
							</Media>
						</SwitchContainer>
						<SwitchContainer SwitchValue="{C61D768C-7BB7-4F28-A38C-243303C01010}">
							<Media>
								<File Id="554847374"/>
							</Media>
						</SwitchContainer>
					</SwitchContainers>
					<ActionSetState>
						<ActionSetStateEntry Id="4059809460" Name="Act_II" ObjectPath="\States\Default Work Unit\BossFase\Act_II"/>
					</ActionSetState>
				</Event>
				<Event Id="1455146363" Name="leg_02_pain" ObjectPath="\Events\Default Work Unit\leg_02_pain">
					<IncludedMemoryFiles>
						<File Id="670178291" Language="SFX">
							<ShortName>leg02_pain_01.wav</ShortName>
							<Path>SFX/leg02_pain_01_10C4C929.wem</Path>
						</File>
						<File Id="1026496876" Language="SFX">
							<ShortName>leg02_pain_02.wav</ShortName>
							<Path>SFX/leg02_pain_02_10C4C929.wem</Path>
						</File>
					</IncludedMemoryFiles>
					<DefaultSwitchValue>{84B70B2B-F10C-497B-8ECA-D9461A3C8CB2}</DefaultSwitchValue>
					<SwitchContainers>
						<SwitchContainer SwitchValue="{84B70B2B-F10C-497B-8ECA-D9461A3C8CB2}">
							<Media>
								<File Id="670178291"/>
							</Media>
						</SwitchContainer>
						<SwitchContainer SwitchValue="{C61D768C-7BB7-4F28-A38C-243303C01010}">
							<Media>
								<File Id="1026496876"/>
							</Media>
						</SwitchContainer>
					</SwitchContainers>
				</Event>
				<Event Id="744354954" Name="leg_attack" ObjectPath="\Events\Default Work Unit\leg_attack">
					<IncludedMemoryFiles>
						<File Id="366659010" Language="SFX">
							<ShortName>leg_attack.wav</ShortName>
							<Path>SFX/leg_attack_10C4C929.wem</Path>
						</File>
					</IncludedMemoryFiles>
				</Event>
				<Event Id="984111278" Name="leg_jump" ObjectPath="\Events\Default Work Unit\leg_jump">
					<IncludedMemoryFiles>
						<File Id="571145463" Language="SFX">
							<ShortName>asari_jump_01.wav</ShortName>
							<Path>SFX/asari_jump_01_10C4C929.wem</Path>
						</File>
						<File Id="597856979" Language="SFX">
							<ShortName>asari_jump_02.wav</ShortName>
							<Path>SFX/asari_jump_02_10C4C929.wem</Path>
						</File>
					</IncludedMemoryFiles>
					<DefaultSwitchValue>{84B70B2B-F10C-497B-8ECA-D9461A3C8CB2}</DefaultSwitchValue>
					<SwitchContainers>
						<SwitchContainer SwitchValue="{84B70B2B-F10C-497B-8ECA-D9461A3C8CB2}">
							<Media>
								<File Id="571145463"/>
							</Media>
						</SwitchContainer>
						<SwitchContainer SwitchValue="{C61D768C-7BB7-4F28-A38C-243303C01010}">
							<Media>
								<File Id="597856979"/>
							</Media>
						</SwitchContainer>
					</SwitchContainers>
				</Event>
				<Event Id="3346849305" Name="leg_land" ObjectPath="\Events\Default Work Unit\leg_land">
					<IncludedMemoryFiles>
						<File Id="439593283" Language="SFX">
							<ShortName>asari_land_01.wav</ShortName>
							<Path>SFX/asari_land_01_10C4C929.wem</Path>
						</File>
						<File Id="691104647" Language="SFX">
							<ShortName>asari_land_02.wav</ShortName>
							<Path>SFX/asari_land_02_10C4C929.wem</Path>
						</File>
					</IncludedMemoryFiles>
					<DefaultSwitchValue>{84B70B2B-F10C-497B-8ECA-D9461A3C8CB2}</DefaultSwitchValue>
					<SwitchContainers>
						<SwitchContainer SwitchValue="{84B70B2B-F10C-497B-8ECA-D9461A3C8CB2}">
							<Media>
								<File Id="439593283"/>
							</Media>
						</SwitchContainer>
						<SwitchContainer SwitchValue="{C61D768C-7BB7-4F28-A38C-243303C01010}">
							<Media>
								<File Id="691104647"/>
							</Media>
						</SwitchContainer>
					</SwitchContainers>
				</Event>
				<Event Id="2643125350" Name="leg_sprint" ObjectPath="\Events\Default Work Unit\leg_sprint">
					<IncludedMemoryFiles>
						<File Id="443334537" Language="SFX">
							<ShortName>legs_sprint_02.wav</ShortName>
							<Path>SFX/legs_sprint_02_10C4C929.wem</Path>
						</File>
						<File Id="1071080517" Language="SFX">
							<ShortName>legs_sprint_01.wav</ShortName>
							<Path>SFX/legs_sprint_01_10C4C929.wem</Path>
						</File>
					</IncludedMemoryFiles>
					<DefaultSwitchValue>{84B70B2B-F10C-497B-8ECA-D9461A3C8CB2}</DefaultSwitchValue>
					<SwitchContainers>
						<SwitchContainer SwitchValue="{84B70B2B-F10C-497B-8ECA-D9461A3C8CB2}">
							<Media>
								<File Id="1071080517"/>
							</Media>
						</SwitchContainer>
						<SwitchContainer SwitchValue="{C61D768C-7BB7-4F28-A38C-243303C01010}">
							<Media>
								<File Id="443334537"/>
							</Media>
						</SwitchContainer>
					</SwitchContainers>
				</Event>
				<Event Id="1048498120" Name="menu_button_pressed" ObjectPath="\Events\Default Work Unit\menu_button_pressed">
					<IncludedMemoryFiles>
						<File Id="654661834" Language="SFX">
							<ShortName>Scorrimento SFX.wav</ShortName>
							<Path>SFX/Scorrimento SFX_856AC20C.wem</Path>
						</File>
					</IncludedMemoryFiles>
					<AuxBusSends>
						<AuxBus Id="3420137967" Name="Menu_Reverb" ObjectPath="\Master-Mixer Hierarchy\Default Work Unit\Master Audio Bus\SFX\Gameplay\Menu_Reverb"/>
					</AuxBusSends>
				</Event>
				<Event Id="2785341881" Name="menu_mouse_over" ObjectPath="\Events\Default Work Unit\menu_mouse_over">
					<IncludedMemoryFiles>
						<File Id="488298735" Language="SFX">
							<ShortName>Selezione SFX.wav</ShortName>
							<Path>SFX/Selezione SFX_B64AB67C.wem</Path>
						</File>
					</IncludedMemoryFiles>
					<AuxBusSends>
						<AuxBus Id="3420137967" Name="Menu_Reverb" ObjectPath="\Master-Mixer Hierarchy\Default Work Unit\Master Audio Bus\SFX\Gameplay\Menu_Reverb"/>
					</AuxBusSends>
				</Event>
				<Event Id="1092296013" Name="menu_play_music" ObjectPath="\Events\Default Work Unit\menu_play_music">
					<IncludedMemoryFiles>
						<File Id="111794383" Language="SFX">
							<ShortName>Drums_114bpm_24beats_Var02.wav</ShortName>
							<Path>SFX/Drums_114bpm_24beats_Var02_E0B2C827.wem</Path>
						</File>
						<File Id="120610167" Language="SFX">
							<ShortName>Pulse_114bpm_24beats_Var02.wav</ShortName>
							<Path>SFX/Pulse_114bpm_24beats_Var02_E0B2C827.wem</Path>
						</File>
						<File Id="190591817" Language="SFX">
							<ShortName>Pulse_114bpm_24beats_Var01.wav</ShortName>
							<Path>SFX/Pulse_114bpm_24beats_Var01_E0B2C827.wem</Path>
						</File>
						<File Id="326274177" Language="SFX">
							<ShortName>EchoSquare_114bpm_24beats_Var02.wav</ShortName>
							<Path>SFX/EchoSquare_114bpm_24beats_Var02_E0B2C827.wem</Path>
						</File>
						<File Id="383395911" Language="SFX">
							<ShortName>EchoSquare_114bpm_24beats_Var03.wav</ShortName>
							<Path>SFX/EchoSquare_114bpm_24beats_Var03_E0B2C827.wem</Path>
						</File>
						<File Id="421570111" Language="SFX">
							<ShortName>Bass_114bpm_24beats_Var02.wav</ShortName>
							<Path>SFX/Bass_114bpm_24beats_Var02_E0B2C827.wem</Path>
						</File>
						<File Id="535090288" Language="SFX">
							<ShortName>Drums_114bpm_24beats_Var03.wav</ShortName>
							<Path>SFX/Drums_114bpm_24beats_Var03_E0B2C827.wem</Path>
						</File>
						<File Id="652904214" Language="SFX">
							<ShortName>Bass_114bpm_24beats_Var01.wav</ShortName>
							<Path>SFX/Bass_114bpm_24beats_Var01_E0B2C827.wem</Path>
						</File>
						<File Id="685133311" Language="SFX">
							<ShortName>Bass_114bpm_24beats_Var03.wav</ShortName>
							<Path>SFX/Bass_114bpm_24beats_Var03_E0B2C827.wem</Path>
						</File>
						<File Id="703875748" Language="SFX">
							<ShortName>EchoSquare_114bpm_24beats_Var01.wav</ShortName>
							<Path>SFX/EchoSquare_114bpm_24beats_Var01_E0B2C827.wem</Path>
						</File>
						<File Id="909193409" Language="SFX">
							<ShortName>Drums_114bpm_24beats_Var01.wav</ShortName>
							<Path>SFX/Drums_114bpm_24beats_Var01_E0B2C827.wem</Path>
						</File>
						<File Id="1038191666" Language="SFX">
							<ShortName>EchoSaw_114bpm_25beats_Var01.wav</ShortName>
							<Path>SFX/EchoSaw_114bpm_25beats_Var01_E0B2C827.wem</Path>
						</File>
					</IncludedMemoryFiles>
				</Event>
				<Event Id="2992688183" Name="metro_play_boss_music" ObjectPath="\Events\Default Work Unit\metro_play_boss_music">
					<IncludedMemoryFiles>
						<File Id="11720279" Language="SFX">
							<ShortName>Lead1_183bpm_24beats_Var1.wav</ShortName>
							<Path>SFX/Lead1_183bpm_24beats_Var1_D79FB2B7.wem</Path>
						</File>
						<File Id="62826312" Language="SFX">
							<ShortName>Drums_183bpm_24beats_Var1.wav</ShortName>
							<Path>SFX/Drums_183bpm_24beats_Var1_D79FB2B7.wem</Path>
						</File>
						<File Id="67444261" Language="SFX">
							<ShortName>Phase 2\Lead2_183bpm_18beats_Var2.wav</ShortName>
							<Path>SFX/Phase 2/Lead2_183bpm_18beats_Var2_D79FB2B7.wem</Path>
						</File>
						<File Id="102016260" Language="SFX">
							<ShortName>Phase 2\Bass_183bpm_24beats_Var1.wav</ShortName>
							<Path>SFX/Phase 2/Bass_183bpm_24beats_Var1_D79FB2B7.wem</Path>
						</File>
						<File Id="167726575" Language="SFX">
							<ShortName>Phase 2\Lead1_183bpm_18beats_Var2.wav</ShortName>
							<Path>SFX/Phase 2/Lead1_183bpm_18beats_Var2_D79FB2B7.wem</Path>
						</File>
						<File Id="330660124" Language="SFX">
							<ShortName>Phase 2\Drums_183bpm_18beats_Var2.wav</ShortName>
							<Path>SFX/Phase 2/Drums_183bpm_18beats_Var2_D79FB2B7.wem</Path>
						</File>
						<File Id="374474568" Language="SFX">
							<ShortName>Phase 2\Bass_183bpm_18beats_Var2.wav</ShortName>
							<Path>SFX/Phase 2/Bass_183bpm_18beats_Var2_D79FB2B7.wem</Path>
						</File>
						<File Id="388459425" Language="SFX">
							<ShortName>Lead2_183bpm_24beats_Var1.wav</ShortName>
							<Path>SFX/Lead2_183bpm_24beats_Var1_D79FB2B7.wem</Path>
						</File>
						<File Id="394856686" Language="SFX">
							<ShortName>Drums_183bpm_18beats_Var2.wav</ShortName>
							<Path>SFX/Drums_183bpm_18beats_Var2_D79FB2B7.wem</Path>
						</File>
						<File Id="416278381" Language="SFX">
							<ShortName>Intro\Bass_183bpm_8beats_Intro.wav</ShortName>
							<Path>SFX/Intro/Bass_183bpm_8beats_Intro_D79FB2B7.wem</Path>
						</File>
						<File Id="584294197" Language="SFX">
							<ShortName>Bass_183bpm_24beats_Var1.wav</ShortName>
							<Path>SFX/Bass_183bpm_24beats_Var1_D79FB2B7.wem</Path>
						</File>
						<File Id="699759549" Language="SFX">
							<ShortName>Bass_183bpm_18beats_Var2.wav</ShortName>
							<Path>SFX/Bass_183bpm_18beats_Var2_D79FB2B7.wem</Path>
						</File>
						<File Id="837141387" Language="SFX">
							<ShortName>Phase 2\Lead2_183bpm_24beats_Var1.wav</ShortName>
							<Path>SFX/Phase 2/Lead2_183bpm_24beats_Var1_D79FB2B7.wem</Path>
						</File>
						<File Id="879140841" Language="SFX">
							<ShortName>LEad1_183bpm_18beats_Var2.wav</ShortName>
							<Path>SFX/LEad1_183bpm_18beats_Var2_D79FB2B7.wem</Path>
						</File>
						<File Id="887747343" Language="SFX">
							<ShortName>Phase 2\Drums_183bpm_24beats_Var1.wav</ShortName>
							<Path>SFX/Phase 2/Drums_183bpm_24beats_Var1_D79FB2B7.wem</Path>
						</File>
						<File Id="916467345" Language="SFX">
							<ShortName>Phase 2\Lead1_183bpm_24beats_Var1.wav</ShortName>
							<Path>SFX/Phase 2/Lead1_183bpm_24beats_Var1_D79FB2B7.wem</Path>
						</File>
						<File Id="1011253626" Language="SFX">
							<ShortName>Intro\Drums_183bpm_8beats_Intro.wav</ShortName>
							<Path>SFX/Intro/Drums_183bpm_8beats_Intro_D79FB2B7.wem</Path>
						</File>
						<File Id="1063228734" Language="SFX">
							<ShortName>Lead2_183bpm_18beats_Var2.wav</ShortName>
							<Path>SFX/Lead2_183bpm_18beats_Var2_D79FB2B7.wem</Path>
						</File>
					</IncludedMemoryFiles>
					<SwitchContainers>
						<SwitchContainer SwitchValue="{84B70B2B-F10C-497B-8ECA-D9461A3C8CB2}">
							<Media>
								<File Id="11720279"/>
								<File Id="62826312"/>
								<File Id="388459425"/>
								<File Id="394856686"/>
								<File Id="584294197"/>
								<File Id="699759549"/>
								<File Id="879140841"/>
								<File Id="1063228734"/>
							</Media>
						</SwitchContainer>
						<SwitchContainer SwitchValue="{C61D768C-7BB7-4F28-A38C-243303C01010}">
							<Media>
								<File Id="67444261"/>
								<File Id="102016260"/>
								<File Id="167726575"/>
								<File Id="330660124"/>
								<File Id="374474568"/>
								<File Id="837141387"/>
								<File Id="887747343"/>
								<File Id="916467345"/>
							</Media>
						</SwitchContainer>
					</SwitchContainers>
				</Event>
				<Event Id="408155869" Name="metro_play_music" ObjectPath="\Events\Default Work Unit\metro_play_music">
					<IncludedMemoryFiles>
						<File Id="5380462" Language="SFX">
							<ShortName>Bass_112bpm_8beats_Main_Var1.wav</ShortName>
							<Path>SFX/Bass_112bpm_8beats_Main_Var1_D79FB2B7.wem</Path>
						</File>
						<File Id="48792539" Language="SFX">
							<ShortName>Drums_112bpm_2beats_Intro.wav</ShortName>
							<Path>SFX/Drums_112bpm_2beats_Intro_D79FB2B7.wem</Path>
						</File>
						<File Id="68395651" Language="SFX">
							<ShortName>Lead_112bpm_16beats_Main_Var2.wav</ShortName>
							<Path>SFX/Lead_112bpm_16beats_Main_Var2_D79FB2B7.wem</Path>
						</File>
						<File Id="173183163" Language="SFX">
							<ShortName>Sine_112bpm_16beats_Main_Var2.wav</ShortName>
							<Path>SFX/Sine_112bpm_16beats_Main_Var2_D79FB2B7.wem</Path>
						</File>
						<File Id="178570768" Language="SFX">
							<ShortName>Drums_112bpm_8beats_Link.wav</ShortName>
							<Path>SFX/Drums_112bpm_8beats_Link_D79FB2B7.wem</Path>
						</File>
						<File Id="287257653" Language="SFX">
							<ShortName>Drums_112bpm_16beats_Main_Var3.wav</ShortName>
							<Path>SFX/Drums_112bpm_16beats_Main_Var3_D79FB2B7.wem</Path>
						</File>
						<File Id="342587765" Language="SFX">
							<ShortName>Bass_112bpm_16beats_Main_Var3.wav</ShortName>
							<Path>SFX/Bass_112bpm_16beats_Main_Var3_D79FB2B7.wem</Path>
						</File>
						<File Id="402677011" Language="SFX">
							<ShortName>Drums_112bpm_16beats_Main_Var2.wav</ShortName>
							<Path>SFX/Drums_112bpm_16beats_Main_Var2_D79FB2B7.wem</Path>
						</File>
						<File Id="433805718" Language="SFX">
							<ShortName>Drums_112bpm_8beats_Main_Var1.wav</ShortName>
							<Path>SFX/Drums_112bpm_8beats_Main_Var1_D79FB2B7.wem</Path>
						</File>
						<File Id="461647819" Language="SFX">
							<ShortName>Sine_112bpm_16beats_Main_Var3.wav</ShortName>
							<Path>SFX/Sine_112bpm_16beats_Main_Var3_D79FB2B7.wem</Path>
						</File>
						<File Id="518538790" Language="SFX">
							<ShortName>Bass_112bpm_8beats_Link.wav</ShortName>
							<Path>SFX/Bass_112bpm_8beats_Link_D79FB2B7.wem</Path>
						</File>
						<File Id="601281915" Language="SFX">
							<ShortName>Bass_112bpm_2beats_Intro.wav</ShortName>
							<Path>SFX/Bass_112bpm_2beats_Intro_D79FB2B7.wem</Path>
						</File>
						<File Id="694855148" Language="SFX">
							<ShortName>Lead_112bpm_8beats_Link.wav</ShortName>
							<Path>SFX/Lead_112bpm_8beats_Link_D79FB2B7.wem</Path>
						</File>
						<File Id="842549490" Language="SFX">
							<ShortName>Lead_112bpm_16beats_Main_Var3.wav</ShortName>
							<Path>SFX/Lead_112bpm_16beats_Main_Var3_D79FB2B7.wem</Path>
						</File>
						<File Id="891284696" Language="SFX">
							<ShortName>Bass_112bpm_16beats_Main_Var2.wav</ShortName>
							<Path>SFX/Bass_112bpm_16beats_Main_Var2_D79FB2B7.wem</Path>
						</File>
						<File Id="948092111" Language="SFX">
							<ShortName>Lead_112bpm_8beats_Main_Var1.wav</ShortName>
							<Path>SFX/Lead_112bpm_8beats_Main_Var1_D79FB2B7.wem</Path>
						</File>
						<File Id="1043356977" Language="SFX">
							<ShortName>Lead_112bpm_2beats_Intro.wav</ShortName>
							<Path>SFX/Lead_112bpm_2beats_Intro_D79FB2B7.wem</Path>
						</File>
					</IncludedMemoryFiles>
					<SwitchContainers>
						<SwitchContainer SwitchValue="{EFE9A17D-6624-4C7D-9FE0-CCE49C1426AA}">
							<Media>
								<File Id="5380462"/>
								<File Id="68395651"/>
								<File Id="173183163"/>
								<File Id="287257653"/>
								<File Id="342587765"/>
								<File Id="402677011"/>
								<File Id="433805718"/>
								<File Id="461647819"/>
								<File Id="842549490"/>
								<File Id="891284696"/>
								<File Id="948092111"/>
							</Media>
						</SwitchContainer>
						<SwitchContainer SwitchValue="{79199A5B-A4C0-4509-A52F-E03D226BA0CF}">
							<Media>
								<File Id="178570768"/>
								<File Id="518538790"/>
								<File Id="694855148"/>
							</Media>
						</SwitchContainer>
					</SwitchContainers>
					<ActionSetState>
						<ActionSetStateEntry Id="2244230815" Name="Safe_Zone" ObjectPath="\States\Default Work Unit\MusicTrigger\Safe_Zone"/>
					</ActionSetState>
				</Event>
				<Event Id="923090826" Name="next_area" ObjectPath="\Events\Default Work Unit\next_area">
					<IncludedMemoryFiles>
						<File Id="776841863" Language="SFX">
							<ShortName>NextLevel.wav</ShortName>
							<Path>SFX/NextLevel_10C4C929.wem</Path>
						</File>
					</IncludedMemoryFiles>
					<AuxBusSends>
						<AuxBus Id="1396213152" Name="Gameplay_Reverb" ObjectPath="\Master-Mixer Hierarchy\Default Work Unit\Master Audio Bus\SFX\Gameplay\Gameplay_Reverb"/>
					</AuxBusSends>
				</Event>
				<Event Id="1405004590" Name="ocean_play_boss_music" ObjectPath="\Events\Default Work Unit\ocean_play_boss_music">
					<IncludedMemoryFiles>
						<File Id="10331457" Language="SFX">
							<ShortName>Bass_157bpm_18beats_Var4.wav</ShortName>
							<Path>SFX/Bass_157bpm_18beats_Var4_E0B2C827.wem</Path>
						</File>
						<File Id="16503182" Language="SFX">
							<ShortName>Bass_157bpm_18beats_Var2.wav</ShortName>
							<Path>SFX/Bass_157bpm_18beats_Var2_E0B2C827.wem</Path>
						</File>
						<File Id="82575238" Language="SFX">
							<ShortName>SquareWave_157bpm_18beats_Var3.wav</ShortName>
							<Path>SFX/SquareWave_157bpm_18beats_Var3_E0B2C827.wem</Path>
						</File>
						<File Id="186136590" Language="SFX">
							<ShortName>Bass_157bpm_18beats_Var1.wav</ShortName>
							<Path>SFX/Bass_157bpm_18beats_Var1_E0B2C827.wem</Path>
						</File>
						<File Id="230371065" Language="SFX">
							<ShortName>SquareWave_157bpm_18beats_Var4.wav</ShortName>
							<Path>SFX/SquareWave_157bpm_18beats_Var4_E0B2C827.wem</Path>
						</File>
						<File Id="295306034" Language="SFX">
							<ShortName>Drums_157bpm_18beats_Var1.wav</ShortName>
							<Path>SFX/Drums_157bpm_18beats_Var1_E0B2C827.wem</Path>
						</File>
						<File Id="354546661" Language="SFX">
							<ShortName>Bass_157bpm_18beats_Var3.wav</ShortName>
							<Path>SFX/Bass_157bpm_18beats_Var3_E0B2C827.wem</Path>
						</File>
						<File Id="563365831" Language="SFX">
							<ShortName>TriangWave_157bpm_18beats_Var2.wav</ShortName>
							<Path>SFX/TriangWave_157bpm_18beats_Var2_E0B2C827.wem</Path>
						</File>
						<File Id="614913155" Language="SFX">
							<ShortName>TriangWave_157bpm_18beats_Var4.wav</ShortName>
							<Path>SFX/TriangWave_157bpm_18beats_Var4_E0B2C827.wem</Path>
						</File>
						<File Id="618500623" Language="SFX">
							<ShortName>TriangWave_157bpm_18beats_Var3.wav</ShortName>
							<Path>SFX/TriangWave_157bpm_18beats_Var3_E0B2C827.wem</Path>
						</File>
						<File Id="681005085" Language="SFX">
							<ShortName>TriangWave_157bpm_18beats_Var1.wav</ShortName>
							<Path>SFX/TriangWave_157bpm_18beats_Var1_E0B2C827.wem</Path>
						</File>
						<File Id="681631620" Language="SFX">
							<ShortName>SquareWave_157bpm_18beats_Var1.wav</ShortName>
							<Path>SFX/SquareWave_157bpm_18beats_Var1_E0B2C827.wem</Path>
						</File>
						<File Id="741114476" Language="SFX">
							<ShortName>Drums_157bpm_18beats_Var2.wav</ShortName>
							<Path>SFX/Drums_157bpm_18beats_Var2_E0B2C827.wem</Path>
						</File>
						<File Id="908616660" Language="SFX">
							<ShortName>Drums_157bpm_18beats_Var3.wav</ShortName>
							<Path>SFX/Drums_157bpm_18beats_Var3_E0B2C827.wem</Path>
						</File>
						<File Id="955700104" Language="SFX">
							<ShortName>Drums_157bpm_18beats_Var4.wav</ShortName>
							<Path>SFX/Drums_157bpm_18beats_Var4_E0B2C827.wem</Path>
						</File>
						<File Id="1061637881" Language="SFX">
							<ShortName>SquareWave_157bpm_18beats_Var2.wav</ShortName>
							<Path>SFX/SquareWave_157bpm_18beats_Var2_E0B2C827.wem</Path>
						</File>
					</IncludedMemoryFiles>
				</Event>
				<Event Id="509704602" Name="ocean_play_music" ObjectPath="\Events\Default Work Unit\ocean_play_music">
					<IncludedMemoryFiles>
						<File Id="78828070" Language="SFX">
							<ShortName>MainSection\Bass_151bpm_16beats_SEC1_Var2.wav</ShortName>
							<Path>SFX/MainSection/Bass_151bpm_16beats_SEC1_Var2_E0B2C827.wem</Path>
						</File>
						<File Id="85672130" Language="SFX">
							<ShortName>Transition\SSC_146bpm_4beats_Trans.wav</ShortName>
							<Path>SFX/Transition/SSC_146bpm_4beats_Trans_E0B2C827.wem</Path>
						</File>
						<File Id="181485881" Language="SFX">
							<ShortName>Intro\SSC_146bpm_15beats_Var2_Intro.wav</ShortName>
							<Path>SFX/Intro/SSC_146bpm_15beats_Var2_Intro_E0B2C827.wem</Path>
						</File>
						<File Id="191988298" Language="SFX">
							<ShortName>MainSection\Drums_151bpm_16beats_SEC1_Var3.wav</ShortName>
							<Path>SFX/MainSection/Drums_151bpm_16beats_SEC1_Var3_E0B2C827.wem</Path>
						</File>
						<File Id="208653305" Language="SFX">
							<ShortName>MainSection\Lead_151bpm_16beats_SEC1_Var3.wav</ShortName>
							<Path>SFX/MainSection/Lead_151bpm_16beats_SEC1_Var3_E0B2C827.wem</Path>
						</File>
						<File Id="213291684" Language="SFX">
							<ShortName>Intro\Farfisa_146bpm_15beats_Var2_Intro.wav</ShortName>
							<Path>SFX/Intro/Farfisa_146bpm_15beats_Var2_Intro_E0B2C827.wem</Path>
						</File>
						<File Id="220920929" Language="SFX">
							<ShortName>Intro\Farfisa_146bpm_15beats_Var1_Intro.wav</ShortName>
							<Path>SFX/Intro/Farfisa_146bpm_15beats_Var1_Intro_E0B2C827.wem</Path>
						</File>
						<File Id="246925947" Language="SFX">
							<ShortName>Intro\SSC_146bpm_15beats_Var3_Intro.wav</ShortName>
							<Path>SFX/Intro/SSC_146bpm_15beats_Var3_Intro_E0B2C827.wem</Path>
						</File>
						<File Id="269230183" Language="SFX">
							<ShortName>MainSection\Bass_151bpm_16beats_SEC2_Var1.wav</ShortName>
							<Path>SFX/MainSection/Bass_151bpm_16beats_SEC2_Var1_E0B2C827.wem</Path>
						</File>
						<File Id="269553334" Language="SFX">
							<ShortName>Transition\Square_146bpm_4beats_Trans.wav</ShortName>
							<Path>SFX/Transition/Square_146bpm_4beats_Trans_E0B2C827.wem</Path>
						</File>
						<File Id="277068223" Language="SFX">
							<ShortName>MainSection\Lead_151bpm_16beats_SEC1_Var2.wav</ShortName>
							<Path>SFX/MainSection/Lead_151bpm_16beats_SEC1_Var2_E0B2C827.wem</Path>
						</File>
						<File Id="345413369" Language="SFX">
							<ShortName>MainSection\Bass_151bpm_16beats_SEC1_Var3.wav</ShortName>
							<Path>SFX/MainSection/Bass_151bpm_16beats_SEC1_Var3_E0B2C827.wem</Path>
						</File>
						<File Id="383666501" Language="SFX">
							<ShortName>MainSection\Bass_151bpm_16beats_SEC1_Var1.wav</ShortName>
							<Path>SFX/MainSection/Bass_151bpm_16beats_SEC1_Var1_E0B2C827.wem</Path>
						</File>
						<File Id="434914832" Language="SFX">
							<ShortName>Intro\Farfisa_146bpm_15beats_Var3_Intro.wav</ShortName>
							<Path>SFX/Intro/Farfisa_146bpm_15beats_Var3_Intro_E0B2C827.wem</Path>
						</File>
						<File Id="494554852" Language="SFX">
							<ShortName>Intro\Drums_146bpm_15beats_Var2_Intro.wav</ShortName>
							<Path>SFX/Intro/Drums_146bpm_15beats_Var2_Intro_E0B2C827.wem</Path>
						</File>
						<File Id="538428245" Language="SFX">
							<ShortName>Intro\Square_146bpm_15beats_Var3_Intro.wav</ShortName>
							<Path>SFX/Intro/Square_146bpm_15beats_Var3_Intro_E0B2C827.wem</Path>
						</File>
						<File Id="649853388" Language="SFX">
							<ShortName>Transition\Drums_146bpm_4beats_Trans.wav</ShortName>
							<Path>SFX/Transition/Drums_146bpm_4beats_Trans_E0B2C827.wem</Path>
						</File>
						<File Id="650777107" Language="SFX">
							<ShortName>MainSection\Lead_151bpm_16beats_SEC1_Var1.wav</ShortName>
							<Path>SFX/MainSection/Lead_151bpm_16beats_SEC1_Var1_E0B2C827.wem</Path>
						</File>
						<File Id="651810435" Language="SFX">
							<ShortName>MainSection\Drums_151bpm_16beats_SEC1_Var2.wav</ShortName>
							<Path>SFX/MainSection/Drums_151bpm_16beats_SEC1_Var2_E0B2C827.wem</Path>
						</File>
						<File Id="683910457" Language="SFX">
							<ShortName>Intro\Square_146bpm_15beats_Var4_Intro.wav</ShortName>
							<Path>SFX/Intro/Square_146bpm_15beats_Var4_Intro_E0B2C827.wem</Path>
						</File>
						<File Id="738404990" Language="SFX">
							<ShortName>Transition\Farfisa_146bpm_4beats_Trans.wav</ShortName>
							<Path>SFX/Transition/Farfisa_146bpm_4beats_Trans_E0B2C827.wem</Path>
						</File>
						<File Id="779131553" Language="SFX">
							<ShortName>Intro\Square_146bpm_15beats_Var2_Intro.wav</ShortName>
							<Path>SFX/Intro/Square_146bpm_15beats_Var2_Intro_E0B2C827.wem</Path>
						</File>
						<File Id="858908446" Language="SFX">
							<ShortName>MainSection\Sine1_151bpm_16beats_SEC2_Var1.wav</ShortName>
							<Path>SFX/MainSection/Sine1_151bpm_16beats_SEC2_Var1_E0B2C827.wem</Path>
						</File>
						<File Id="880060666" Language="SFX">
							<ShortName>MainSection\Drums_151bpm_16beats_SEC2_Var1.wav</ShortName>
							<Path>SFX/MainSection/Drums_151bpm_16beats_SEC2_Var1_E0B2C827.wem</Path>
						</File>
						<File Id="917706819" Language="SFX">
							<ShortName>MainSection\Sine2_151bpm_16beats_SEC2_Var1.wav</ShortName>
							<Path>SFX/MainSection/Sine2_151bpm_16beats_SEC2_Var1_E0B2C827.wem</Path>
						</File>
						<File Id="933889380" Language="SFX">
							<ShortName>Intro\Square_146bpm_15beats_Var1_Intro.wav</ShortName>
							<Path>SFX/Intro/Square_146bpm_15beats_Var1_Intro_E0B2C827.wem</Path>
						</File>
						<File Id="1011049950" Language="SFX">
							<ShortName>Intro\SSC_146bpm_15beats_Var1_Intro.wav</ShortName>
							<Path>SFX/Intro/SSC_146bpm_15beats_Var1_Intro_E0B2C827.wem</Path>
						</File>
						<File Id="1012994847" Language="SFX">
							<ShortName>Intro\Drums_146bpm_15beats_Var1_Intro.wav</ShortName>
							<Path>SFX/Intro/Drums_146bpm_15beats_Var1_Intro_E0B2C827.wem</Path>
						</File>
						<File Id="1026891249" Language="SFX">
							<ShortName>MainSection\Drums_151bpm_16beats_SEC1_Var1.wav</ShortName>
							<Path>SFX/MainSection/Drums_151bpm_16beats_SEC1_Var1_E0B2C827.wem</Path>
						</File>
					</IncludedMemoryFiles>
					<SwitchContainers>
						<SwitchContainer SwitchValue="{79199A5B-A4C0-4509-A52F-E03D226BA0CF}">
							<Media>
								<File Id="181485881"/>
								<File Id="213291684"/>
								<File Id="220920929"/>
								<File Id="246925947"/>
								<File Id="434914832"/>
								<File Id="494554852"/>
								<File Id="538428245"/>
								<File Id="683910457"/>
								<File Id="779131553"/>
								<File Id="933889380"/>
								<File Id="1011049950"/>
								<File Id="1012994847"/>
							</Media>
						</SwitchContainer>
						<SwitchContainer SwitchValue="{EFE9A17D-6624-4C7D-9FE0-CCE49C1426AA}">
							<Media>
								<File Id="78828070"/>
								<File Id="191988298"/>
								<File Id="208653305"/>
								<File Id="269230183"/>
								<File Id="277068223"/>
								<File Id="345413369"/>
								<File Id="383666501"/>
								<File Id="650777107"/>
								<File Id="651810435"/>
								<File Id="858908446"/>
								<File Id="880060666"/>
								<File Id="917706819"/>
								<File Id="1026891249"/>
							</Media>
						</SwitchContainer>
					</SwitchContainers>
				</Event>
				<Event Id="1086145255" Name="pick_up_heal" ObjectPath="\Events\Default Work Unit\pick_up_heal">
					<IncludedMemoryFiles>
						<File Id="670840965" Language="SFX">
							<ShortName>heal.wav</ShortName>
							<Path>SFX/heal_10C4C929.wem</Path>
						</File>
					</IncludedMemoryFiles>
					<AuxBusSends>
						<AuxBus Id="1396213152" Name="Gameplay_Reverb" ObjectPath="\Master-Mixer Hierarchy\Default Work Unit\Master Audio Bus\SFX\Gameplay\Gameplay_Reverb"/>
					</AuxBusSends>
				</Event>
				<Event Id="405565217" Name="salarian_attack" ObjectPath="\Events\Default Work Unit\salarian_attack">
					<IncludedMemoryFiles>
						<File Id="376785801" Language="SFX">
							<ShortName>Salarian_Hit.wav</ShortName>
							<Path>SFX/Salarian_Hit_10C4C929.wem</Path>
						</File>
						<File Id="610709990" Language="SFX">
							<ShortName>Salarian_Hit_1.wav</ShortName>
							<Path>SFX/Salarian_Hit_1_10C4C929.wem</Path>
						</File>
					</IncludedMemoryFiles>
				</Event>
				<Event Id="3201417669" Name="salarian_death" ObjectPath="\Events\Default Work Unit\salarian_death">
					<IncludedMemoryFiles>
						<File Id="64664951" Language="SFX">
							<ShortName>Salarian_Death.wav</ShortName>
							<Path>SFX/Salarian_Death_10C4C929.wem</Path>
						</File>
						<File Id="424646652" Language="SFX">
							<ShortName>Salarian_Death_Special.wav</ShortName>
							<Path>SFX/Salarian_Death_Special_10C4C929.wem</Path>
						</File>
						<File Id="505063809" Language="SFX">
							<ShortName>Salarian_Death_1.wav</ShortName>
							<Path>SFX/Salarian_Death_1_10C4C929.wem</Path>
						</File>
					</IncludedMemoryFiles>
				</Event>
				<Event Id="3656616932" Name="salarian_hit" ObjectPath="\Events\Default Work Unit\salarian_hit">
					<IncludedMemoryFiles>
						<File Id="187779727" Language="SFX">
							<ShortName>Salarian_Hurt_1.wav</ShortName>
							<Path>SFX/Salarian_Hurt_1_36DF9909.wem</Path>
						</File>
						<File Id="455554793" Language="SFX">
							<ShortName>Salarian_Hurt.wav</ShortName>
							<Path>SFX/Salarian_Hurt_36DF9909.wem</Path>
						</File>
					</IncludedMemoryFiles>
				</Event>
				<Event Id="3962179328" Name="station_play_boss_music" ObjectPath="\Events\Default Work Unit\station_play_boss_music">
					<IncludedMemoryFiles>
						<File Id="21709813" Language="SFX">
							<ShortName>Intro\Lead1_157bpm_8beats_Intro.wav</ShortName>
							<Path>SFX/Intro/Lead1_157bpm_8beats_Intro_D79FB2B7.wem</Path>
						</File>
						<File Id="107601844" Language="SFX">
							<ShortName>Main\Lead1_157bpm_16beats_Ivar1.wav</ShortName>
							<Path>SFX/Main/Lead1_157bpm_16beats_Ivar1_D79FB2B7.wem</Path>
						</File>
						<File Id="189900006" Language="SFX">
							<ShortName>Main\Drums_157bpm_16beats_Ivar2.wav</ShortName>
							<Path>SFX/Main/Drums_157bpm_16beats_Ivar2_D79FB2B7.wem</Path>
						</File>
						<File Id="241402291" Language="SFX">
							<ShortName>Main\Lead1_157bpm_16beats_Ivar2.wav</ShortName>
							<Path>SFX/Main/Lead1_157bpm_16beats_Ivar2_D79FB2B7.wem</Path>
						</File>
						<File Id="301207349" Language="SFX">
							<ShortName>Main\Bass_157bpm_16beats_Ivar2.wav</ShortName>
							<Path>SFX/Main/Bass_157bpm_16beats_Ivar2_D79FB2B7.wem</Path>
						</File>
						<File Id="413192090" Language="SFX">
							<ShortName>Main\Lead2_157bpm_16beats_Ivar1.wav</ShortName>
							<Path>SFX/Main/Lead2_157bpm_16beats_Ivar1_D79FB2B7.wem</Path>
						</File>
						<File Id="490625729" Language="SFX">
							<ShortName>Main\Drums_157bpm_16beats_Ivar1.wav</ShortName>
							<Path>SFX/Main/Drums_157bpm_16beats_Ivar1_D79FB2B7.wem</Path>
						</File>
						<File Id="509098013" Language="SFX">
							<ShortName>Intro\Lead2_157bpm_8beats_Intro.wav</ShortName>
							<Path>SFX/Intro/Lead2_157bpm_8beats_Intro_D79FB2B7.wem</Path>
						</File>
						<File Id="762856936" Language="SFX">
							<ShortName>Main\Bass_157bpm_16beats_Ivar1.wav</ShortName>
							<Path>SFX/Main/Bass_157bpm_16beats_Ivar1_D79FB2B7.wem</Path>
						</File>
						<File Id="1008114300" Language="SFX">
							<ShortName>Intro\Bass_157bpm_8beats_Intro.wav</ShortName>
							<Path>SFX/Intro/Bass_157bpm_8beats_Intro_D79FB2B7.wem</Path>
						</File>
						<File Id="1037439366" Language="SFX">
							<ShortName>Intro\Drums_157bpm_8beats_Intro.wav</ShortName>
							<Path>SFX/Intro/Drums_157bpm_8beats_Intro_D79FB2B7.wem</Path>
						</File>
						<File Id="1059517764" Language="SFX">
							<ShortName>Main\Lead2_157bpm_16beats_Ivar2.wav</ShortName>
							<Path>SFX/Main/Lead2_157bpm_16beats_Ivar2_D79FB2B7.wem</Path>
						</File>
					</IncludedMemoryFiles>
				</Event>
				<Event Id="2703159004" Name="station_play_music" ObjectPath="\Events\Default Work Unit\station_play_music">
					<IncludedMemoryFiles>
						<File Id="49177610" Language="SFX">
							<ShortName>Sfx_156bpm_32beats_Main_Var2.wav</ShortName>
							<Path>SFX/Sfx_156bpm_32beats_Main_Var2_D79FB2B7.wem</Path>
						</File>
						<File Id="113652576" Language="SFX">
							<ShortName>Lead_156bpm_16beats_Main_Var1.wav</ShortName>
							<Path>SFX/Lead_156bpm_16beats_Main_Var1_D79FB2B7.wem</Path>
						</File>
						<File Id="136305509" Language="SFX">
							<ShortName>Bass_156bpm_32beats_Main_Var2.wav</ShortName>
							<Path>SFX/Bass_156bpm_32beats_Main_Var2_D79FB2B7.wem</Path>
						</File>
						<File Id="214469969" Language="SFX">
							<ShortName>Bass_156bpm_4beats_Link.wav</ShortName>
							<Path>SFX/Bass_156bpm_4beats_Link_D79FB2B7.wem</Path>
						</File>
						<File Id="387524531" Language="SFX">
							<ShortName>Drums_156bpm_32beats_Main_Var2.wav</ShortName>
							<Path>SFX/Drums_156bpm_32beats_Main_Var2_D79FB2B7.wem</Path>
						</File>
						<File Id="603198863" Language="SFX">
							<ShortName>Bass_156bpm_16beats_Main_Var3.wav</ShortName>
							<Path>SFX/Bass_156bpm_16beats_Main_Var3_D79FB2B7.wem</Path>
						</File>
						<File Id="692367739" Language="SFX">
							<ShortName>Lead_156bpm_32beats_Main_Var2.wav</ShortName>
							<Path>SFX/Lead_156bpm_32beats_Main_Var2_D79FB2B7.wem</Path>
						</File>
						<File Id="728062307" Language="SFX">
							<ShortName>Drums_156bpm_16beats_Main_Var3.wav</ShortName>
							<Path>SFX/Drums_156bpm_16beats_Main_Var3_D79FB2B7.wem</Path>
						</File>
						<File Id="732782623" Language="SFX">
							<ShortName>Pad_156bpm_32beats_Main_Var2.wav</ShortName>
							<Path>SFX/Pad_156bpm_32beats_Main_Var2_D79FB2B7.wem</Path>
						</File>
						<File Id="748661819" Language="SFX">
							<ShortName>Sfx_156bpm_12beats_Intro.wav</ShortName>
							<Path>SFX/Sfx_156bpm_12beats_Intro_D79FB2B7.wem</Path>
						</File>
						<File Id="793377606" Language="SFX">
							<ShortName>Sfx_156bpm_16beats_Main_Var3.wav</ShortName>
							<Path>SFX/Sfx_156bpm_16beats_Main_Var3_D79FB2B7.wem</Path>
						</File>
						<File Id="802839322" Language="SFX">
							<ShortName>Bass_156bpm_12beats_Intro.wav</ShortName>
							<Path>SFX/Bass_156bpm_12beats_Intro_D79FB2B7.wem</Path>
						</File>
						<File Id="820854580" Language="SFX">
							<ShortName>Drums_156bpm_16beats_Main_Var1.wav</ShortName>
							<Path>SFX/Drums_156bpm_16beats_Main_Var1_D79FB2B7.wem</Path>
						</File>
						<File Id="854211825" Language="SFX">
							<ShortName>Drums_156bpm_12beats_Intro.wav</ShortName>
							<Path>SFX/Drums_156bpm_12beats_Intro_D79FB2B7.wem</Path>
						</File>
						<File Id="1011917791" Language="SFX">
							<ShortName>Bass_156bpm_16beats_Main_Var1.wav</ShortName>
							<Path>SFX/Bass_156bpm_16beats_Main_Var1_D79FB2B7.wem</Path>
						</File>
						<File Id="1050580590" Language="SFX">
							<ShortName>Drums_156bpm_4beats_Link.wav</ShortName>
							<Path>SFX/Drums_156bpm_4beats_Link_D79FB2B7.wem</Path>
						</File>
					</IncludedMemoryFiles>
					<SwitchContainers>
						<SwitchContainer SwitchValue="{79199A5B-A4C0-4509-A52F-E03D226BA0CF}">
							<Media>
								<File Id="748661819"/>
								<File Id="802839322"/>
								<File Id="854211825"/>
							</Media>
						</SwitchContainer>
						<SwitchContainer SwitchValue="{EFE9A17D-6624-4C7D-9FE0-CCE49C1426AA}">
							<Media>
								<File Id="49177610"/>
								<File Id="113652576"/>
								<File Id="136305509"/>
								<File Id="387524531"/>
								<File Id="603198863"/>
								<File Id="692367739"/>
								<File Id="728062307"/>
								<File Id="732782623"/>
								<File Id="793377606"/>
								<File Id="820854580"/>
								<File Id="1011917791"/>
							</Media>
						</SwitchContainer>
					</SwitchContainers>
				</Event>
				<Event Id="1815802421" Name="turian_attack" ObjectPath="\Events\Default Work Unit\turian_attack">
					<IncludedMemoryFiles>
						<File Id="288753623" Language="SFX">
							<ShortName>Turian_Hit.wav</ShortName>
							<Path>SFX/Turian_Hit_10C4C929.wem</Path>
						</File>
						<File Id="1042665136" Language="SFX">
							<ShortName>Turian_Hit_1.wav</ShortName>
							<Path>SFX/Turian_Hit_1_10C4C929.wem</Path>
						</File>
					</IncludedMemoryFiles>
				</Event>
				<Event Id="440684361" Name="turian_death" ObjectPath="\Events\Default Work Unit\turian_death">
					<IncludedMemoryFiles>
						<File Id="651147191" Language="SFX">
							<ShortName>Turian_Death_1.wav</ShortName>
							<Path>SFX/Turian_Death_1_10C4C929.wem</Path>
						</File>
						<File Id="1029542451" Language="SFX">
							<ShortName>Turian_Death.wav</ShortName>
							<Path>SFX/Turian_Death_10C4C929.wem</Path>
						</File>
					</IncludedMemoryFiles>
				</Event>
				<Event Id="1251247560" Name="turian_hit" ObjectPath="\Events\Default Work Unit\turian_hit">
					<IncludedMemoryFiles>
						<File Id="170246256" Language="SFX">
							<ShortName>Turian_Hurt_1.wav</ShortName>
							<Path>SFX/Turian_Hurt_1_10C4C929.wem</Path>
						</File>
						<File Id="177164356" Language="SFX">
							<ShortName>Turian_Hurt.wav</ShortName>
							<Path>SFX/Turian_Hurt_10C4C929.wem</Path>
						</File>
					</IncludedMemoryFiles>
				</Event>
				<Event Id="4280871310" Name="vine_death" ObjectPath="\Events\Default Work Unit\vine_death">
					<IncludedMemoryFiles>
						<File Id="367103396" Language="SFX">
							<ShortName>TheVine_Death.wav</ShortName>
							<Path>SFX/TheVine_Death_36DF9909.wem</Path>
						</File>
					</IncludedMemoryFiles>
				</Event>
				<Event Id="3793263743" Name="vine_hit" ObjectPath="\Events\Default Work Unit\vine_hit">
					<IncludedMemoryFiles>
						<File Id="50656336" Language="SFX">
							<ShortName>TheVine_Pain_1.wav</ShortName>
							<Path>SFX/TheVine_Pain_1_10C4C929.wem</Path>
						</File>
						<File Id="683335489" Language="SFX">
							<ShortName>TheVine_Pain.wav</ShortName>
							<Path>SFX/TheVine_Pain_10C4C929.wem</Path>
						</File>
					</IncludedMemoryFiles>
				</Event>
				<Event Id="2504136357" Name="vine_knockback" ObjectPath="\Events\Default Work Unit\vine_knockback">
					<IncludedMemoryFiles>
						<File Id="856789115" Language="SFX">
							<ShortName>TheVine_Knockback.wav</ShortName>
							<Path>SFX/TheVine_Knockback_10C4C929.wem</Path>
						</File>
					</IncludedMemoryFiles>
				</Event>
				<Event Id="3224572430" Name="vine_plant_grow_down" ObjectPath="\Events\Default Work Unit\vine_plant_grow_down">
					<IncludedMemoryFiles>
						<File Id="958198027" Language="SFX">
							<ShortName>TheVine_PlantGrowthDown_1.wav</ShortName>
							<Path>SFX/TheVine_PlantGrowthDown_1_A6ACC5D3.wem</Path>
						</File>
						<File Id="993215685" Language="SFX">
							<ShortName>TheVine_PlantGrowthDown.wav</ShortName>
							<Path>SFX/TheVine_PlantGrowthDown_10C4C929.wem</Path>
						</File>
					</IncludedMemoryFiles>
				</Event>
				<Event Id="2895845717" Name="vine_plant_grow_up" ObjectPath="\Events\Default Work Unit\vine_plant_grow_up">
					<IncludedMemoryFiles>
						<File Id="529669070" Language="SFX">
							<ShortName>TheVine_PlantGrowthUp.wav</ShortName>
							<Path>SFX/TheVine_PlantGrowthUp_10C4C929.wem</Path>
						</File>
						<File Id="548273777" Language="SFX">
							<ShortName>TheVine_PlantGrowthUp_2.wav</ShortName>
							<Path>SFX/TheVine_PlantGrowthUp_2_10C4C929.wem</Path>
						</File>
						<File Id="600286783" Language="SFX">
							<ShortName>TheVine_PlantGrowthUp_1.wav</ShortName>
							<Path>SFX/TheVine_PlantGrowthUp_1_10C4C929.wem</Path>
						</File>
					</IncludedMemoryFiles>
				</Event>
				<Event Id="1165879959" Name="vine_plant_shoot" ObjectPath="\Events\Default Work Unit\vine_plant_shoot">
					<IncludedMemoryFiles>
						<File Id="556907126" Language="SFX">
							<ShortName>TheVine_PlantShoot.wav</ShortName>
							<Path>SFX/TheVine_PlantShoot_0D967A07.wem</Path>
						</File>
						<File Id="741401470" Language="SFX">
							<ShortName>TheVine_PlantShoot_1.wav</ShortName>
							<Path>SFX/TheVine_PlantShoot_1_10C4C929.wem</Path>
						</File>
					</IncludedMemoryFiles>
				</Event>
				<Event Id="953546913" Name="volcan_play_boss_music" ObjectPath="\Events\Default Work Unit\volcan_play_boss_music">
					<IncludedMemoryFiles>
						<File Id="4430693" Language="SFX">
							<ShortName>Lead1_Act_III.wav</ShortName>
							<Path>SFX/Lead1_Act_III_D79FB2B7.wem</Path>
						</File>
						<File Id="138221904" Language="SFX">
							<ShortName>Drum_Act_III.wav</ShortName>
							<Path>SFX/Drum_Act_III_D79FB2B7.wem</Path>
						</File>
						<File Id="220860623" Language="SFX">
							<ShortName>Bass_Act_III.wav</ShortName>
							<Path>SFX/Bass_Act_III_D79FB2B7.wem</Path>
						</File>
						<File Id="397181214" Language="SFX">
							<ShortName>Drums_146bpm_12beats_Var1.wav</ShortName>
							<Path>SFX/Drums_146bpm_12beats_Var1_D79FB2B7.wem</Path>
						</File>
						<File Id="571103197" Language="SFX">
							<ShortName>Bass_146bpm_8beats_Intro.wav</ShortName>
							<Path>SFX/Bass_146bpm_8beats_Intro_D79FB2B7.wem</Path>
						</File>
						<File Id="629646762" Language="SFX">
							<ShortName>Lead2_146bpm_12beats_Var1.wav</ShortName>
							<Path>SFX/Lead2_146bpm_12beats_Var1_D79FB2B7.wem</Path>
						</File>
						<File Id="721329600" Language="SFX">
							<ShortName>Drums_146bpm_8beats_Intro.wav</ShortName>
							<Path>SFX/Drums_146bpm_8beats_Intro_D79FB2B7.wem</Path>
						</File>
						<File Id="763629569" Language="SFX">
							<ShortName>Bass_146bpm_12beats_Var1.wav</ShortName>
							<Path>SFX/Bass_146bpm_12beats_Var1_D79FB2B7.wem</Path>
						</File>
						<File Id="939918078" Language="SFX">
							<ShortName>Lead2_Act_III.wav</ShortName>
							<Path>SFX/Lead2_Act_III_D79FB2B7.wem</Path>
						</File>
						<File Id="953079061" Language="SFX">
							<ShortName>Lead1_146bpm_12beats_Var1.wav</ShortName>
							<Path>SFX/Lead1_146bpm_12beats_Var1_D79FB2B7.wem</Path>
						</File>
					</IncludedMemoryFiles>
					<SwitchContainers>
						<SwitchContainer SwitchValue="{84B70B2B-F10C-497B-8ECA-D9461A3C8CB2}">
							<Media>
								<File Id="571103197"/>
								<File Id="721329600"/>
							</Media>
						</SwitchContainer>
						<SwitchContainer SwitchValue="{C61D768C-7BB7-4F28-A38C-243303C01010}">
							<Media>
								<File Id="397181214"/>
								<File Id="629646762"/>
								<File Id="763629569"/>
								<File Id="953079061"/>
							</Media>
						</SwitchContainer>
						<SwitchContainer SwitchValue="{A97014C2-3DDD-4A7F-8122-ADEA83AD1341}">
							<Media>
								<File Id="4430693"/>
								<File Id="138221904"/>
								<File Id="220860623"/>
								<File Id="939918078"/>
							</Media>
						</SwitchContainer>
					</SwitchContainers>
				</Event>
				<Event Id="2640247479" Name="volcan_play_music" ObjectPath="\Events\Default Work Unit\volcan_play_music">
					<IncludedMemoryFiles>
						<File Id="67608110" Language="SFX">
							<ShortName>Bass_Var1_146.wav</ShortName>
							<Path>SFX/Bass_Var1_146_E0B2C827.wem</Path>
						</File>
						<File Id="150829689" Language="SFX">
							<ShortName>Drum_Intro.wav</ShortName>
							<Path>SFX/Drum_Intro_E0B2C827.wem</Path>
						</File>
						<File Id="322926687" Language="SFX">
							<ShortName>Lead1_Intro.wav</ShortName>
							<Path>SFX/Lead1_Intro_E0B2C827.wem</Path>
						</File>
						<File Id="348711085" Language="SFX">
							<ShortName>Bass_Intro_146.wav</ShortName>
							<Path>SFX/Bass_Intro_146_E0B2C827.wem</Path>
						</File>
						<File Id="367627437" Language="SFX">
							<ShortName>Bass_Var2_146.wav</ShortName>
							<Path>SFX/Bass_Var2_146_E0B2C827.wem</Path>
						</File>
						<File Id="650571315" Language="SFX">
							<ShortName>Drum_Transition.wav</ShortName>
							<Path>SFX/Drum_Transition_D79FB2B7.wem</Path>
						</File>
						<File Id="884768478" Language="SFX">
							<ShortName>Bass_Transition_146.wav</ShortName>
							<Path>SFX/Bass_Transition_146_D79FB2B7.wem</Path>
						</File>
						<File Id="911747919" Language="SFX">
							<ShortName>Drum_Var1.wav</ShortName>
							<Path>SFX/Drum_Var1_E0B2C827.wem</Path>
						</File>
						<File Id="939947047" Language="SFX">
							<ShortName>Drum_Var2.wav</ShortName>
							<Path>SFX/Drum_Var2_E0B2C827.wem</Path>
						</File>
						<File Id="940444652" Language="SFX">
							<ShortName>Lead1_Var1.wav</ShortName>
							<Path>SFX/Lead1_Var1_E0B2C827.wem</Path>
						</File>
						<File Id="944213011" Language="SFX">
							<ShortName>Lead2.wav</ShortName>
							<Path>SFX/Lead2_E0B2C827.wem</Path>
						</File>
						<File Id="983833803" Language="SFX">
							<ShortName>Lead1_Var2.wav</ShortName>
							<Path>SFX/Lead1_Var2_E0B2C827.wem</Path>
						</File>
					</IncludedMemoryFiles>
					<SwitchContainers>
						<SwitchContainer SwitchValue="{79199A5B-A4C0-4509-A52F-E03D226BA0CF}">
							<Media>
								<File Id="150829689"/>
								<File Id="322926687"/>
								<File Id="348711085"/>
							</Media>
						</SwitchContainer>
						<SwitchContainer SwitchValue="{EFE9A17D-6624-4C7D-9FE0-CCE49C1426AA}">
							<Media>
								<File Id="67608110"/>
								<File Id="367627437"/>
								<File Id="911747919"/>
								<File Id="939947047"/>
								<File Id="940444652"/>
								<File Id="944213011"/>
								<File Id="983833803"/>
							</Media>
						</SwitchContainer>
					</SwitchContainers>
				</Event>
			</IncludedEvents>
			<StateGroups>
				<StateGroup Id="1206119301" Name="BossFase" ObjectPath="\States\Default Work Unit\BossFase" GUID="{FC35E302-3C27-46D7-8948-CE289257BA68}">
					<States>
						<State Id="748895195" Name="None" ObjectPath="\States\Default Work Unit\BossFase\None" GUID="{D6199DF4-02DE-4740-8A68-EF73C6E51240}"/>
						<State Id="1408244687" Name="Act_I" ObjectPath="\States\Default Work Unit\BossFase\Act_I" GUID="{84B70B2B-F10C-497B-8ECA-D9461A3C8CB2}"/>
						<State Id="4059809460" Name="Act_II" ObjectPath="\States\Default Work Unit\BossFase\Act_II" GUID="{C61D768C-7BB7-4F28-A38C-243303C01010}"/>
						<State Id="2740571445" Name="Act_III" ObjectPath="\States\Default Work Unit\BossFase\Act_III" GUID="{A97014C2-3DDD-4A7F-8122-ADEA83AD1341}"/>
					</States>
				</StateGroup>
				<StateGroup Id="1927797142" Name="MusicTrigger" ObjectPath="\States\Default Work Unit\MusicTrigger" GUID="{96697E5E-130C-4DA5-B5E5-6EA9704D8853}">
					<States>
						<State Id="748895195" Name="None" ObjectPath="\States\Default Work Unit\MusicTrigger\None" GUID="{CC38A415-16BE-4607-839C-ADA2902C3399}"/>
						<State Id="2244230815" Name="Safe_Zone" ObjectPath="\States\Default Work Unit\MusicTrigger\Safe_Zone" GUID="{79199A5B-A4C0-4509-A52F-E03D226BA0CF}"/>
						<State Id="2764240573" Name="Combat" ObjectPath="\States\Default Work Unit\MusicTrigger\Combat" GUID="{EFE9A17D-6624-4C7D-9FE0-CCE49C1426AA}"/>
						<State Id="2716678721" Name="Victory" ObjectPath="\States\Default Work Unit\MusicTrigger\Victory" GUID="{10ED56CC-FCE7-4BBD-9760-EAE9150F8F25}"/>
						<State Id="1593864692" Name="Defeat" ObjectPath="\States\Default Work Unit\MusicTrigger\Defeat" GUID="{10F37216-78D0-418F-A547-F782AE205D2C}"/>
					</States>
				</StateGroup>
				<StateGroup Id="2244230815" Name="Safe_Zone" ObjectPath="\States\Default Work Unit\MusicTrigger\Safe_Zone" GUID="{79199A5B-A4C0-4509-A52F-E03D226BA0CF}">
					<States/>
				</StateGroup>
				<StateGroup Id="2740571445" Name="Act_III" ObjectPath="\States\Default Work Unit\BossFase\Act_III" GUID="{A97014C2-3DDD-4A7F-8122-ADEA83AD1341}">
					<States/>
				</StateGroup>
				<StateGroup Id="4059809460" Name="Act_II" ObjectPath="\States\Default Work Unit\BossFase\Act_II" GUID="{C61D768C-7BB7-4F28-A38C-243303C01010}">
					<States/>
				</StateGroup>
			</StateGroups>
		</SoundBank>
	</SoundBanks>
</SoundBanksInfo>
